Workbook

Sheet Budget
A1: year | B1: month | C1: business_unit | D1: budgeted_revenue | E1: budgeted_expense | F1: Actual _expense _helper col | G1: BUDGETED EXPENSE_helper col | H1: BUDGET VARIANCE | I1: Budget_Variance_Outlier_Flag
A2: 2022 | B2: 1 | C2: Retail | D2: 1530660 | E2: 1259760 | F2: =ABS(SUMIFS(Financial_Transactions!C:C,Financial_Transactions!F:F,Budget!C2,Financial_Transactions!L:L,Budget!B2,Financial_Transactions!M:M,Budget!A2)) -> 5412829.7 | G2: =SUMIFS(E:E,C:C,Budget!C2,B:B,Budget!B2,A:A,Budget!A2) -> 1259760 | H2: =F2-G2 -> 4153069.7 | I2: =IF(H2="","", IF(OR(H2 < EDA_Outlier_Analysis!$M$10, H2 > EDA_Outlier_Analysis!$M$11), "Outlier", "Normal")) -> Normal
A3: 2022 | B3: 1 | C3: Enterprise | D3: 1689240 | E3: 1152615 | F3: =ABS(SUMIFS(Financial_Transactions!C:C,Financial_Transactions!F:F,Budget!C3,Financial_Transactions!L:L,Budget!B3,Financial_Transactions!M:M,Budget!A3)) -> 6939353.9 | G3: =SUMIFS(E:E,C:C,Budget!C3,B:B,Budget!B3,A:A,Budget!A3) -> 1152615 | H3: =F3-G3 -> 5786738.9 | I3: =IF(H3="","", IF(OR(H3 < EDA_Outlier_Analysis!$M$10, H3 > EDA_Outlier_Analysis!$M$11), "Outlier", "Normal")) -> Normal
A4: 2022 | B4: 1 | C4: Online | D4: 2069088 | E4: 1776169 | F4: =ABS(SUMIFS(Financial_Transactions!C:C,Financial_Transactions!F:F,Budget!C4,Financial_Transactions!L:L,Budget!B4,Financial_Transactions!M:M,Budget!A4)) -> 6584819.9 | G4: =SUMIFS(E:E,C:C,Budget!C4,B:B,Budget!B4,A:A,Budget!A4) -> 1776169 | H4: =F4-G4 -> 4808650.9 | I4: =IF(H4="","", IF(OR(H4 < EDA_Outlier_Analysis!$M$10, H4 > EDA_Outlier_Analysis!$M$11), "Outlier", "Normal")) -> Normal
A5: 2022 | B5: 2 | C5: Retail | D5: 1836984 | E5: 1201730 | F5: =ABS(SUMIFS(Financial_Transactions!C:C,Financial_Transactions!F:F,Budget!C5,Financial_Transactions!L:L,Budget!B5,Financial_Transactions!M:M,Budget!A5)) -> 7080862.7 | G5: =SUMIFS(E:E,C:C,Budget!C5,B:B,Budget!B5,A:A,Budget!A5) -> 1201730 | H5: =F5-G5 -> 5879132.7 | I5: =IF(H5="","", IF(OR(H5 < EDA_Outlier_Analysis!$M$10, H5 > EDA_Outlier_Analysis!$M$11), "Outlier", "Normal")) -> Normal
A6: 2022 | B6: 2 | C6: Enterprise | D6: 1923012 | E6: 1454263 | F6: =ABS(SUMIFS(Financial_Transactions!C:C,Financial_Transactions!F:F,Budget!C6,Financial_Transactions!L:L,Budget!B6,Financial_Transactions!M:M,Budget!A6)) -> 5236074.5 | G6: =SUMIFS(E:E,C:C,Budget!C6,B:B,Budget!B6,A:A,Budget!A6) -> 1454263 | H6: =F6-G6 -> 3781811.5 | I6: =IF(H6="","", IF(OR(H6 < EDA_Outlier_Analysis!$M$10, H6 > EDA_Outlier_Analysis!$M$11), "Outlier", "Normal")) -> Normal
A7: 2022 | B7: 2 | C7: Online | D7: 1516272 | E7: 1117069 | F7: =ABS(SUMIFS(Financial_Transactions!C:C,Financial_Transactions!F:F,Budget!C7,Financial_Transactions!L:L,Budget!B7,Financial_Transactions!M:M,Budget!A7)) -> 4984247.5 | G7: =SUMIFS(E:E,C:C,Budget!C7,B:B,Budget!B7,A:A,Budget!A7) -> 1117069 | H7: =F7-G7 -> 3867178.5 | I7: =IF(H7="","", IF(OR(H7 < EDA_Outlier_Analysis!$M$10, H7 > EDA_Outlier_Analysis!$M$11), "Outlier", "Normal")) -> Normal
A8: 2022 | B8: 3 | C8: Retail | D8: 1510920 | E8: 1106833 | F8: =ABS(SUMIFS(Financial_Transactions!C:C,Financial_Transactions!F:F,Budget!C8,Financial_Transactions!L:L,Budget!B8,Financial_Transactions!M:M,Budget!A8)) -> 4751090.3 | G8: =SUMIFS(E:E,C:C,Budget!C8,B:B,Budget!B8,A:A,Budget!A8) -> 1106833 | H8: =F8-G8 -> 3644257.3 | I8: =IF(H8="","", IF(OR(H8 < EDA_Outlier_Analysis!$M$10, H8 > EDA_Outlier_Analysis!$M$11), "Outlier", "Normal")) -> Normal
A9: 2022 | B9: 3 | C9: Enterprise | D9: 1576692 | E9: 959653 | F9: =ABS(SUMIFS(Financial_Transactions!C:C,Financial_Transactions!F:F,Budget!C9,Financial_Transactions!L:L,Budget!B9,Financial_Transactions!M:M,Budget!A9)) -> 7072144.3 | G9: =SUMIFS(E:E,C:C,Budget!C9,B:B,Budget!B9,A:A,Budget!A9) -> 959653 | H9: =F9-G9 -> 6112491.3 | I9: =IF(H9="","", IF(OR(H9 < EDA_Outlier_Analysis!$M$10, H9 > EDA_Outlier_Analysis!$M$11), "Outlier", "Normal")) -> Normal
A10: 2022 | B10: 3 | C10: Online | D10: 2119464 | E10: 1677676 | F10: =ABS(SUMIFS(Financial_Transactions!C:C,Financial_Transactions!F:F,Budget!C10,Financial_Transactions!L:L,Budget!B10,Financial_Transactions!M:M,Budget!A10)) -> 7911633 | G10: =SUMIFS(E:E,C:C,Budget!C10,B:B,Budget!B10,A:A,Budget!A10) -> 1677676 | H10: =F10-G10 -> 6233957 | I10: =IF(H10="","", IF(OR(H10 < EDA_Outlier_Analysis!$M$10, H10 > EDA_Outlier_Analysis!$M$11), "Outlier", "Normal")) -> Normal
A11: 2022 | B11: 4 | C11: Retail | D11: 1731204 | E11: 1275919 | F11: =ABS(SUMIFS(Financial_Transactions!C:C,Financial_Transactions!F:F,Budget!C11,Financial_Transactions!L:L,Budget!B11,Financial_Transactions!M:M,Budget!A11)) -> 7684580.3 | G11: =SUMIFS(E:E,C:C,Budget!C11,B:B,Budget!B11,A:A,Budget!A11) -> 1275919 | H11: =F11-G11 -> 6408661.3 | I11: =IF(H11="","", IF(OR(H11 < EDA_Outlier_Analysis!$M$10, H11 > EDA_Outlier_Analysis!$M$11), "Outlier", "Normal")) -> Normal
A12: 2022 | B12: 4 | C12: Enterprise | D12: 2042184 | E12: 1592655 | F12: =ABS(SUMIFS(Financial_Transactions!C:C,Financial_Transactions!F:F,Budget!C12,Financial_Transactions!L:L,Budget!B12,Financial_Transactions!M:M,Budget!A12)) -> 8597751.4 | G12: =SUMIFS(E:E,C:C,Budget!C12,B:B,Budget!B12,A:A,Budget!A12) -> 1592655 | H12: =F12-G12 -> 7005096.4 | I12: =IF(H12="","", IF(OR(H12 < EDA_Outlier_Analysis!$M$10, H12 > EDA_Outlier_Analysis!$M$11), "Outlier", "Normal")) -> Normal
A13: 2022 | B13: 4 | C13: Online | D13: 2132844 | E13: 1388082 | F13: =ABS(SUMIFS(Financial_Transactions!C:C,Financial_Transactions!F:F,Budget!C13,Financial_Transactions!L:L,Budget!B13,Financial_Transactions!M:M,Budget!A13)) -> 9740610.3 | G13: =SUMIFS(E:E,C:C,Budget!C13,B:B,Budget!B13,A:A,Budget!A13) -> 1388082 | H13: =F13-G13 -> 8352528.3 | I13: =IF(H13="","", IF(OR(H13 < EDA_Outlier_Analysis!$M$10, H13 > EDA_Outlier_Analysis!$M$11), "Outlier", "Normal")) -> Normal
... A73: 2023 | B73: 12 | C73: Online | D73: 2263008 | E73: 1662605 | F73: =ABS(SUMIFS(Financial_Transactions!C:C,Financial_Transactions!F:F,Budget!C73,Financial_Transactions!L:L,Budget!B73,Financial_Transactions!M:M,Budget!A73)) -> 15321099 | G73: =SUMIFS(E:E,C:C,Budget!C73,B:B,Budget!B73,A:A,Budget!A73) -> 1662605 | H73: =F73-G73 -> 13658494 | I73: =IF(H73="","", IF(OR(H73 < EDA_Outlier_Analysis!$M$10, H73 > EDA_Outlier_Analysis!$M$11), "Outlier", "Normal")) -> Normal

Sheet Customers
A1: customer_id | B1: customer_name | C1: segment | D1: join_date | E1: region | F1: status
A2: CUST10000 | B2: Johnson, Olson and Smith | C2: Online | D2: 43918 | E2: North | F2: Active
A3: CUST10001 | B3: Colon-Valdez | C3: Enterprise | D3: 43146 | E3: West | F3: Active
A4: CUST10002 | B4: Henry, Jones and Farley | C4: Online | D4: 44641 | E4: North | F4: Active
A5: CUST10003 | B5: Williams-Dalton | C5: Retail | D5: 44277 | E5: West | F5: Active
A6: CUST10004 | B6: Fisher-Serrano | C6: Enterprise | D6: 43406 | E6: East | F6: Active
A7: CUST10005 | B7: Jennings Ltd | C7: Online | D7: 43663 | E7: South | F7: Active
A8: CUST10006 | B8: Tate-Haas | C8: Retail | D8: 45212 | E8: West | F8: Active
A9: CUST10007 | B9: Brooks, Aguilar and Young | C9: Enterprise | D9: 43234 | E9: North | F9: Active
A10: CUST10008 | B10: Herrera-Ingram | C10: Retail | D10: 43350 | E10: East | F10: Active
A11: CUST10009 | B11: Dunn, Graham and Brown | C11: Retail | D11: 44229 | E11: West | F11: Active
A12: CUST10010 | B12: Moore, Walker and Gutierrez | C12: Retail | D12: 42831 | E12: East | F12: Active
A13: CUST10011 | B13: Turner-Lawson | C13: Enterprise | D13: 42920 | E13: West | F13: Active
... A401: CUST10399 | B401: Marshall-Horne | C401: Enterprise | D401: 43563 | E401: East | F401: Inactive

Sheet Financial_Transactions
A1: transaction_id | B1: transaction_date | C1: amount | D1: account_type | E1: category | F1: business_unit | G1: region | H1: customer_id | I1: vendor_id | J1: description | K1: customer_fk_status | L1: Month | M1: year | N1: Profit _Value | O1: Revenue_Value | P1: Expense_Value | Q1: Revenue_Outlier_Flag | R1: Expense_Outlier_Flag | S1: Profit_Outlier_Flag
A2: TRX100000 | B2: 45172 | C2: -66631.73 | D2: Expense | E2: Supplies | F2: Online | G2: West | I2: VEND1053 | J2: Begin catch control dark practice. | K2: =IF(COUNTIF(Customers!A:A, H2)>0, "Valid", "Invalid") -> Invalid | L2: =TEXT(B2,"m") -> 9 | M2: =TEXT(B2,"yyyy") -> 2023 | N2: =IF(D2="Revenue",C2,-ABS(C2)) -> -66631.73 | O2: =IF(D2="Revenue", C2, "") | P2: =IF(D2="Expense", ABS(C2), "") -> 66631.73 | Q2: =IF(O2="","", IF(OR(O2<EDA_Outlier_Analysis!$C$10, O2>EDA_Outlier_Analysis!$C$11), "Outlier", "Normal")) | R2: =IF(P2="","", IF(OR(P2 < EDA_Outlier_Analysis!$F$7, P2 > EDA_Outlier_Analysis!$F$8), "Outlier", "Normal")) -> Outlier | S2: =IF(N2="","", IF(OR(N2 <EDA_Outlier_Analysis!$I$10, N2 > EDA_Outlier_Analysis!$I$11), "Outlier", "Normal")) -> Normal
A3: TRX100001 | B3: 45182 | C3: -54305.58 | D3: Expense | E3: Utilities | F3: Enterprise | G3: East | I3: VEND1059 | J3: Style guy soldier boy energy above. | K3: =IF(COUNTIF(Customers!A:A, H3)>0, "Valid", "Invalid") -> Invalid | L3: =TEXT(B3,"m") -> 9 | M3: =TEXT(B3,"yyyy") -> 2023 | N3: =IF(D3="Revenue",C3,-ABS(C3)) -> -54305.58 | O3: =IF(D3="Revenue", C3, "") | P3: =IF(D3="Expense", ABS(C3), "") -> 54305.58 | Q3: =IF(O3="","", IF(OR(O3<EDA_Outlier_Analysis!$C$10, O3>EDA_Outlier_Analysis!$C$11), "Outlier", "Normal")) | R3: =IF(P3="","", IF(OR(P3 < EDA_Outlier_Analysis!$F$7, P3 > EDA_Outlier_Analysis!$F$8), "Outlier", "Normal")) -> Outlier | S3: =IF(N3="","", IF(OR(N3 <EDA_Outlier_Analysis!$I$10, N3 > EDA_Outlier_Analysis!$I$11), "Outlier", "Normal")) -> Normal
A4: TRX100002 | B4: 45104 | C4: 146074.92 | D4: Revenue | E4: Subscription | F4: Online | G4: East | H4: CUST10122 | J4: Skill surface drug personal western. | K4: =IF(COUNTIF(Customers!A:A, H4)>0, "Valid", "Invalid") -> Valid | L4: =TEXT(B4,"m") -> 6 | M4: =TEXT(B4,"yyyy") -> 2023 | N4: =IF(D4="Revenue",C4,-ABS(C4)) -> 146074.92 | O4: =IF(D4="Revenue", C4, "") -> 146074.92 | P4: =IF(D4="Expense", ABS(C4), "") | Q4: =IF(O4="","", IF(OR(O4<EDA_Outlier_Analysis!$C$10, O4>EDA_Outlier_Analysis!$C$11), "Outlier", "Normal")) -> Normal | R4: =IF(P4="","", IF(OR(P4 < EDA_Outlier_Analysis!$F$7, P4 > EDA_Outlier_Analysis!$F$8), "Outlier", "Normal")) | S4: =IF(N4="","", IF(OR(N4 <EDA_Outlier_Analysis!$I$10, N4 > EDA_Outlier_Analysis!$I$11), "Outlier", "Normal")) -> Normal
A5: TRX100003 | B5: 45102 | C5: 212157.95 | D5: Revenue | E5: Service | F5: Enterprise | G5: West | H5: CUST10027 | J5: Develop many it I rich floor decide. | K5: =IF(COUNTIF(Customers!A:A, H5)>0, "Valid", "Invalid") -> Valid | L5: =TEXT(B5,"m") -> 6 | M5: =TEXT(B5,"yyyy") -> 2023 | N5: =IF(D5="Revenue",C5,-ABS(C5)) -> 212157.95 | O5: =IF(D5="Revenue", C5, "") -> 212157.95 | P5: =IF(D5="Expense", ABS(C5), "") | Q5: =IF(O5="","", IF(OR(O5<EDA_Outlier_Analysis!$C$10, O5>EDA_Outlier_Analysis!$C$11), "Outlier", "Normal")) -> Normal | R5: =IF(P5="","", IF(OR(P5 < EDA_Outlier_Analysis!$F$7, P5 > EDA_Outlier_Analysis!$F$8), "Outlier", "Normal")) | S5: =IF(N5="","", IF(OR(N5 <EDA_Outlier_Analysis!$I$10, N5 > EDA_Outlier_Analysis!$I$11), "Outlier", "Normal")) -> Normal
A6: TRX100004 | B6: 45245 | C6: -35944.73 | D6: Expense | E6: Rent | F6: Enterprise | G6: North | I6: VEND1046 | J6: Choose thought teach never. | K6: =IF(COUNTIF(Customers!A:A, H6)>0, "Valid", "Invalid") -> Invalid | L6: =TEXT(B6,"m") -> 11 | M6: =TEXT(B6,"yyyy") -> 2023 | N6: =IF(D6="Revenue",C6,-ABS(C6)) -> -35944.73 | O6: =IF(D6="Revenue", C6, "") | P6: =IF(D6="Expense", ABS(C6), "") -> 35944.73 | Q6: =IF(O6="","", IF(OR(O6<EDA_Outlier_Analysis!$C$10, O6>EDA_Outlier_Analysis!$C$11), "Outlier", "Normal")) | R6: =IF(P6="","", IF(OR(P6 < EDA_Outlier_Analysis!$F$7, P6 > EDA_Outlier_Analysis!$F$8), "Outlier", "Normal")) -> Normal | S6: =IF(N6="","", IF(OR(N6 <EDA_Outlier_Analysis!$I$10, N6 > EDA_Outlier_Analysis!$I$11), "Outlier", "Normal")) -> Normal
A7: TRX100005 | B7: 44989 | C7: 90953.83 | D7: Revenue | E7: Service | F7: Retail | G7: South | H7: CUST10332 | J7: Dinner present unit lay course. | K7: =IF(COUNTIF(Customers!A:A, H7)>0, "Valid", "Invalid") -> Valid | L7: =TEXT(B7,"m") -> 3 | M7: =TEXT(B7,"yyyy") -> 2023 | N7: =IF(D7="Revenue",C7,-ABS(C7)) -> 90953.83 | O7: =IF(D7="Revenue", C7, "") -> 90953.83 | P7: =IF(D7="Expense", ABS(C7), "") | Q7: =IF(O7="","", IF(OR(O7<EDA_Outlier_Analysis!$C$10, O7>EDA_Outlier_Analysis!$C$11), "Outlier", "Normal")) -> Normal | R7: =IF(P7="","", IF(OR(P7 < EDA_Outlier_Analysis!$F$7, P7 > EDA_Outlier_Analysis!$F$8), "Outlier", "Normal")) | S7: =IF(N7="","", IF(OR(N7 <EDA_Outlier_Analysis!$I$10, N7 > EDA_Outlier_Analysis!$I$11), "Outlier", "Normal")) -> Normal
A8: TRX100006 | B8: 45115 | C8: 73251.21 | D8: Revenue | E8: Service | F8: Online | G8: West | H8: CUST10270 | J8: Data ago arm care hundred represent wonder. | K8: =IF(COUNTIF(Customers!A:A, H8)>0, "Valid", "Invalid") -> Valid | L8: =TEXT(B8,"m") -> 7 | M8: =TEXT(B8,"yyyy") -> 2023 | N8: =IF(D8="Revenue",C8,-ABS(C8)) -> 73251.21 | O8: =IF(D8="Revenue", C8, "") -> 73251.21 | P8: =IF(D8="Expense", ABS(C8), "") | Q8: =IF(O8="","", IF(OR(O8<EDA_Outlier_Analysis!$C$10, O8>EDA_Outlier_Analysis!$C$11), "Outlier", "Normal")) -> Normal | R8: =IF(P8="","", IF(OR(P8 < EDA_Outlier_Analysis!$F$7, P8 > EDA_Outlier_Analysis!$F$8), "Outlier", "Normal")) | S8: =IF(N8="","", IF(OR(N8 <EDA_Outlier_Analysis!$I$10, N8 > EDA_Outlier_Analysis!$I$11), "Outlier", "Normal")) -> Normal
A9: TRX100007 | B9: 44644 | C9: -21064.02 | D9: Expense | E9: Marketing | F9: Online | G9: East | I9: VEND1115 | J9: Sign such remember range ability. | K9: =IF(COUNTIF(Customers!A:A, H9)>0, "Valid", "Invalid") -> Invalid | L9: =TEXT(B9,"m") -> 3 | M9: =TEXT(B9,"yyyy") -> 2022 | N9: =IF(D9="Revenue",C9,-ABS(C9)) -> -21064.02 | O9: =IF(D9="Revenue", C9, "") | P9: =IF(D9="Expense", ABS(C9), "") -> 21064.02 | Q9: =IF(O9="","", IF(OR(O9<EDA_Outlier_Analysis!$C$10, O9>EDA_Outlier_Analysis!$C$11), "Outlier", "Normal")) | R9: =IF(P9="","", IF(OR(P9 < EDA_Outlier_Analysis!$F$7, P9 > EDA_Outlier_Analysis!$F$8), "Outlier", "Normal")) -> Outlier | S9: =IF(N9="","", IF(OR(N9 <EDA_Outlier_Analysis!$I$10, N9 > EDA_Outlier_Analysis!$I$11), "Outlier", "Normal")) -> Normal
A10: TRX100008 | B10: 44775 | C10: 136347.73 | D10: Revenue | E10: Product | F10: Retail | G10: West | H10: CUST10168 | J10: Poor similar feeling close require probably rather thought. | K10: =IF(COUNTIF(Customers!A:A, H10)>0, "Valid", "Invalid") -> Valid | L10: =TEXT(B10,"m") -> 8 | M10: =TEXT(B10,"yyyy") -> 2022 | N10: =IF(D10="Revenue",C10,-ABS(C10)) -> 136347.73 | O10: =IF(D10="Revenue", C10, "") -> 136347.73 | P10: =IF(D10="Expense", ABS(C10), "") | Q10: =IF(O10="","", IF(OR(O10<EDA_Outlier_Analysis!$C$10, O10>EDA_Outlier_Analysis!$C$11), "Outlier", "Normal")) -> Normal | R10: =IF(P10="","", IF(OR(P10 < EDA_Outlier_Analysis!$F$7, P10 > EDA_Outlier_Analysis!$F$8), "Outlier", "Normal")) | S10: =IF(N10="","", IF(OR(N10 <EDA_Outlier_Analysis!$I$10, N10 > EDA_Outlier_Analysis!$I$11), "Outlier", "Normal")) -> Normal
A11: TRX100009 | B11: 45094 | C11: 159482 | D11: Revenue | E11: Product | F11: Retail | G11: West | H11: CUST10151 | J11: Cause worker statement office able foot. | K11: =IF(COUNTIF(Customers!A:A, H11)>0, "Valid", "Invalid") -> Valid | L11: =TEXT(B11,"m") -> 6 | M11: =TEXT(B11,"yyyy") -> 2023 | N11: =IF(D11="Revenue",C11,-ABS(C11)) -> 159482 | O11: =IF(D11="Revenue", C11, "") -> 159482 | P11: =IF(D11="Expense", ABS(C11), "") | Q11: =IF(O11="","", IF(OR(O11<EDA_Outlier_Analysis!$C$10, O11>EDA_Outlier_Analysis!$C$11), "Outlier", "Normal")) -> Normal | R11: =IF(P11="","", IF(OR(P11 < EDA_Outlier_Analysis!$F$7, P11 > EDA_Outlier_Analysis!$F$8), "Outlier", "Normal")) | S11: =IF(N11="","", IF(OR(N11 <EDA_Outlier_Analysis!$I$10, N11 > EDA_Outlier_Analysis!$I$11), "Outlier", "Normal")) -> Normal
A12: TRX100010 | B12: 44749 | C12: 15882.36 | D12: Equity | E12: Equity | F12: Retail | G12: South | J12: Ready enter quite attack resource list commercial. | K12: =IF(COUNTIF(Customers!A:A, H12)>0, "Valid", "Invalid") -> Invalid | L12: =TEXT(B12,"m") -> 7 | M12: =TEXT(B12,"yyyy") -> 2022 | N12: =IF(D12="Revenue",C12,-ABS(C12)) -> -15882.36 | O12: =IF(D12="Revenue", C12, "") | P12: =IF(D12="Expense", ABS(C12), "") | Q12: =IF(O12="","", IF(OR(O12<EDA_Outlier_Analysis!$C$10, O12>EDA_Outlier_Analysis!$C$11), "Outlier", "Normal")) | R12: =IF(P12="","", IF(OR(P12 < EDA_Outlier_Analysis!$F$7, P12 > EDA_Outlier_Analysis!$F$8), "Outlier", "Normal")) | S12: =IF(N12="","", IF(OR(N12 <EDA_Outlier_Analysis!$I$10, N12 > EDA_Outlier_Analysis!$I$11), "Outlier", "Normal")) -> Normal
A13: TRX100011 | B13: 44781 | C13: 217487.82 | D13: Revenue | E13: Product | F13: Online | G13: North | H13: CUST10353 | J13: Before green media feeling Mr half trouble. | K13: =IF(COUNTIF(Customers!A:A, H13)>0, "Valid", "Invalid") -> Valid | L13: =TEXT(B13,"m") -> 8 | M13: =TEXT(B13,"yyyy") -> 2022 | N13: =IF(D13="Revenue",C13,-ABS(C13)) -> 217487.82 | O13: =IF(D13="Revenue", C13, "") -> 217487.82 | P13: =IF(D13="Expense", ABS(C13), "") | Q13: =IF(O13="","", IF(OR(O13<EDA_Outlier_Analysis!$C$10, O13>EDA_Outlier_Analysis!$C$11), "Outlier", "Normal")) -> Normal | R13: =IF(P13="","", IF(OR(P13 < EDA_Outlier_Analysis!$F$7, P13 > EDA_Outlier_Analysis!$F$8), "Outlier", "Normal")) | S13: =IF(N13="","", IF(OR(N13 <EDA_Outlier_Analysis!$I$10, N13 > EDA_Outlier_Analysis!$I$11), "Outlier", "Normal")) -> Normal
A14: TRX100012 | B14: 45001 | C14: -8913.27 | D14: Expense | E14: Other | F14: Enterprise | G14: East | I14: VEND1067 | J14: Rise discover visit security end buy medical think. | K14: =IF(COUNTIF(Customers!A:A, H14)>0, "Valid", "Invalid") -> Invalid | L14: =TEXT(B14,"m") -> 3 | M14: =TEXT(B14,"yyyy") -> 2023 | N14: =IF(D14="Revenue",C14,-ABS(C14)) -> -8913.27 | O14: =IF(D14="Revenue", C14, "") | P14: =IF(D14="Expense", ABS(C14), "") -> 8913.27 | Q14: =IF(O14="","", IF(OR(O14<EDA_Outlier_Analysis!$C$10, O14>EDA_Outlier_Analysis!$C$11), "Outlier", "Normal")) | R14: =IF(P14="","", IF(OR(P14 < EDA_Outlier_Analysis!$F$7, P14 > EDA_Outlier_Analysis!$F$8), "Outlier", "Normal")) -> Outlier | S14: =IF(N14="","", IF(OR(N14 <EDA_Outlier_Analysis!$I$10, N14 > EDA_Outlier_Analysis!$I$11), "Outlier", "Normal")) -> Normal
A15: TRX100013 | B15: 45270 | C15: 139523.96 | D15: Revenue | E15: Service | F15: Retail | G15: North | H15: CUST10243 | J15: Military line exist little education family world. | K15: =IF(COUNTIF(Customers!A:A, H15)>0, "Valid", "Invalid") -> Valid | L15: =TEXT(B15,"m") -> 12 | M15: =TEXT(B15,"yyyy") -> 2023 | N15: =IF(D15="Revenue",C15,-ABS(C15)) -> 139523.96 | O15: =IF(D15="Revenue", C15, "") -> 139523.96 | P15: =IF(D15="Expense", ABS(C15), "") | Q15: =IF(O15="","", IF(OR(O15<EDA_Outlier_Analysis!$C$10, O15>EDA_Outlier_Analysis!$C$11), "Outlier", "Normal")) -> Normal | R15: =IF(P15="","", IF(OR(P15 < EDA_Outlier_Analysis!$F$7, P15 > EDA_Outlier_Analysis!$F$8), "Outlier", "Normal")) | S15: =IF(N15="","", IF(OR(N15 <EDA_Outlier_Analysis!$I$10, N15 > EDA_Outlier_Analysis!$I$11), "Outlier", "Normal")) -> Normal
A16: TRX100014 | B16: 45125 | C16: 165589.04 | D16: Revenue | E16: Service | F16: Online | G16: East | H16: CUST10357 | J16: Artist place loss morning. | K16: =IF(COUNTIF(Customers!A:A, H16)>0, "Valid", "Invalid") -> Valid | L16: =TEXT(B16,"m") -> 7 | M16: =TEXT(B16,"yyyy") -> 2023 | N16: =IF(D16="Revenue",C16,-ABS(C16)) -> 165589.04 | O16: =IF(D16="Revenue", C16, "") -> 165589.04 | P16: =IF(D16="Expense", ABS(C16), "") | Q16: =IF(O16="","", IF(OR(O16<EDA_Outlier_Analysis!$C$10, O16>EDA_Outlier_Analysis!$C$11), "Outlier", "Normal")) -> Normal | R16: =IF(P16="","", IF(OR(P16 < EDA_Outlier_Analysis!$F$7, P16 > EDA_Outlier_Analysis!$F$8), "Outlier", "Normal")) | S16: =IF(N16="","", IF(OR(N16 <EDA_Outlier_Analysis!$I$10, N16 > EDA_Outlier_Analysis!$I$11), "Outlier", "Normal")) -> Normal
A17: TRX100015 | B17: 44952 | C17: 262541.15 | D17: Revenue | E17: Service | F17: Retail | G17: West | H17: CUST10045 | J17: Game evidence support skill pretty. | K17: =IF(COUNTIF(Customers!A:A, H17)>0, "Valid", "Invalid") -> Valid | L17: =TEXT(B17,"m") -> 1 | M17: =TEXT(B17,"yyyy") -> 2023 | N17: =IF(D17="Revenue",C17,-ABS(C17)) -> 262541.15 | O17: =IF(D17="Revenue", C17, "") -> 262541.15 | P17: =IF(D17="Expense", ABS(C17), "") | Q17: =IF(O17="","", IF(OR(O17<EDA_Outlier_Analysis!$C$10, O17>EDA_Outlier_Analysis!$C$11), "Outlier", "Normal")) -> Normal | R17: =IF(P17="","", IF(OR(P17 < EDA_Outlier_Analysis!$F$7, P17 > EDA_Outlier_Analysis!$F$8), "Outlier", "Normal")) | S17: =IF(N17="","", IF(OR(N17 <EDA_Outlier_Analysis!$I$10, N17 > EDA_Outlier_Analysis!$I$11), "Outlier", "Normal")) -> Normal
A18: TRX100016 | B18: 45087 | C18: 152113.39 | D18: Revenue | E18: Service | F18: Online | G18: South | H18: CUST10120 | J18: Bad author generation decade increase. | K18: =IF(COUNTIF(Customers!A:A, H18)>0, "Valid", "Invalid") -> Valid | L18: =TEXT(B18,"m") -> 6 | M18: =TEXT(B18,"yyyy") -> 2023 | N18: =IF(D18="Revenue",C18,-ABS(C18)) -> 152113.39 | O18: =IF(D18="Revenue", C18, "") -> 152113.39 | P18: =IF(D18="Expense", ABS(C18), "") | Q18: =IF(O18="","", IF(OR(O18<EDA_Outlier_Analysis!$C$10, O18>EDA_Outlier_Analysis!$C$11), "Outlier", "Normal")) -> Normal | R18: =IF(P18="","", IF(OR(P18 < EDA_Outlier_Analysis!$F$7, P18 > EDA_Outlier_Analysis!$F$8), "Outlier", "Normal")) | S18: =IF(N18="","", IF(OR(N18 <EDA_Outlier_Analysis!$I$10, N18 > EDA_Outlier_Analysis!$I$11), "Outlier", "Normal")) -> Normal
A19: TRX100017 | B19: 44726 | C19: 107495.7 | D19: Revenue | E19: Service | F19: Online | G19: North | H19: CUST10228 | J19: Left own eat wife tell with. | K19: =IF(COUNTIF(Customers!A:A, H19)>0, "Valid", "Invalid") -> Valid | L19: =TEXT(B19,"m") -> 6 | M19: =TEXT(B19,"yyyy") -> 2022 | N19: =IF(D19="Revenue",C19,-ABS(C19)) -> 107495.7 | O19: =IF(D19="Revenue", C19, "") -> 107495.7 | P19: =IF(D19="Expense", ABS(C19), "") | Q19: =IF(O19="","", IF(OR(O19<EDA_Outlier_Analysis!$C$10, O19>EDA_Outlier_Analysis!$C$11), "Outlier", "Normal")) -> Normal | R19: =IF(P19="","", IF(OR(P19 < EDA_Outlier_Analysis!$F$7, P19 > EDA_Outlier_Analysis!$F$8), "Outlier", "Normal")) | S19: =IF(N19="","", IF(OR(N19 <EDA_Outlier_Analysis!$I$10, N19 > EDA_Outlier_Analysis!$I$11), "Outlier", "Normal")) -> Normal
A20: TRX100018 | B20: 45190 | C20: 83127.62 | D20: Revenue | E20: Subscription | F20: Online | G20: West | H20: CUST10333 | J20: Individual first region. | K20: =IF(COUNTIF(Customers!A:A, H20)>0, "Valid", "Invalid") -> Valid | L20: =TEXT(B20,"m") -> 9 | M20: =TEXT(B20,"yyyy") -> 2023 | N20: =IF(D20="Revenue",C20,-ABS(C20)) -> 83127.62 | O20: =IF(D20="Revenue", C20, "") -> 83127.62 | P20: =IF(D20="Expense", ABS(C20), "") | Q20: =IF(O20="","", IF(OR(O20<EDA_Outlier_Analysis!$C$10, O20>EDA_Outlier_Analysis!$C$11), "Outlier", "Normal")) -> Normal | R20: =IF(P20="","", IF(OR(P20 < EDA_Outlier_Analysis!$F$7, P20 > EDA_Outlier_Analysis!$F$8), "Outlier", "Normal")) | S20: =IF(N20="","", IF(OR(N20 <EDA_Outlier_Analysis!$I$10, N20 > EDA_Outlier_Analysis!$I$11), "Outlier", "Normal")) -> Normal
A21: TRX100019 | B21: 44793 | C21: 145634.47 | D21: Revenue | E21: Service | F21: Enterprise | G21: West | H21: CUST10302 | J21: Rise war shake doctor. | K21: =IF(COUNTIF(Customers!A:A, H21)>0, "Valid", "Invalid") -> Valid | L21: =TEXT(B21,"m") -> 8 | M21: =TEXT(B21,"yyyy") -> 2022 | N21: =IF(D21="Revenue",C21,-ABS(C21)) -> 145634.47 | O21: =IF(D21="Revenue", C21, "") -> 145634.47 | P21: =IF(D21="Expense", ABS(C21), "") | Q21: =IF(O21="","", IF(OR(O21<EDA_Outlier_Analysis!$C$10, O21>EDA_Outlier_Analysis!$C$11), "Outlier", "Normal")) -> Normal | R21: =IF(P21="","", IF(OR(P21 < EDA_Outlier_Analysis!$F$7, P21 > EDA_Outlier_Analysis!$F$8), "Outlier", "Normal")) | S21: =IF(N21="","", IF(OR(N21 <EDA_Outlier_Analysis!$I$10, N21 > EDA_Outlier_Analysis!$I$11), "Outlier", "Normal")) -> Normal
A22: TRX100020 | B22: 45062 | C22: 167566.97 | D22: Revenue | E22: Service | F22: Retail | G22: North | H22: CUST10042 | J22: Before expect allow job one set. | K22: =IF(COUNTIF(Customers!A:A, H22)>0, "Valid", "Invalid") -> Valid | L22: =TEXT(B22,"m") -> 5 | M22: =TEXT(B22,"yyyy") -> 2023 | N22: =IF(D22="Revenue",C22,-ABS(C22)) -> 167566.97 | O22: =IF(D22="Revenue", C22, "") -> 167566.97 | P22: =IF(D22="Expense", ABS(C22), "") | Q22: =IF(O22="","", IF(OR(O22<EDA_Outlier_Analysis!$C$10, O22>EDA_Outlier_Analysis!$C$11), "Outlier", "Normal")) -> Normal | R22: =IF(P22="","", IF(OR(P22 < EDA_Outlier_Analysis!$F$7, P22 > EDA_Outlier_Analysis!$F$8), "Outlier", "Normal")) | S22: =IF(N22="","", IF(OR(N22 <EDA_Outlier_Analysis!$I$10, N22 > EDA_Outlier_Analysis!$I$11), "Outlier", "Normal")) -> Normal
A23: TRX100021 | B23: 44726 | C23: -2000 | D23: Expense | E23: Rent | F23: Online | G23: West | I23: VEND1022 | J23: Side official leave seem financial. | K23: =IF(COUNTIF(Customers!A:A, H23)>0, "Valid", "Invalid") -> Invalid | L23: =TEXT(B23,"m") -> 6 | M23: =TEXT(B23,"yyyy") -> 2022 | N23: =IF(D23="Revenue",C23,-ABS(C23)) -> -2000 | O23: =IF(D23="Revenue", C23, "") | P23: =IF(D23="Expense", ABS(C23), "") -> 2000 | Q23: =IF(O23="","", IF(OR(O23<EDA_Outlier_Analysis!$C$10, O23>EDA_Outlier_Analysis!$C$11), "Outlier", "Normal")) | R23: =IF(P23="","", IF(OR(P23 < EDA_Outlier_Analysis!$F$7, P23 > EDA_Outlier_Analysis!$F$8), "Outlier", "Normal")) -> Outlier | S23: =IF(N23="","", IF(OR(N23 <EDA_Outlier_Analysis!$I$10, N23 > EDA_Outlier_Analysis!$I$11), "Outlier", "Normal")) -> Normal
A24: TRX100022 | B24: 44998 | C24: 203374.65 | D24: Revenue | E24: Service | F24: Online | G24: South | H24: CUST10021 | J24: Must require bit relate Congress local improve organization. | K24: =IF(COUNTIF(Customers!A:A, H24)>0, "Valid", "Invalid") -> Valid | L24: =TEXT(B24,"m") -> 3 | M24: =TEXT(B24,"yyyy") -> 2023 | N24: =IF(D24="Revenue",C24,-ABS(C24)) -> 203374.65 | O24: =IF(D24="Revenue", C24, "") -> 203374.65 | P24: =IF(D24="Expense", ABS(C24), "") | Q24: =IF(O24="","", IF(OR(O24<EDA_Outlier_Analysis!$C$10, O24>EDA_Outlier_Analysis!$C$11), "Outlier", "Normal")) -> Normal | R24: =IF(P24="","", IF(OR(P24 < EDA_Outlier_Analysis!$F$7, P24 > EDA_Outlier_Analysis!$F$8), "Outlier", "Normal")) | S24: =IF(N24="","", IF(OR(N24 <EDA_Outlier_Analysis!$I$10, N24 > EDA_Outlier_Analysis!$I$11), "Outlier", "Normal")) -> Normal
A25: TRX100023 | B25: 45189 | C25: 171433.19 | D25: Revenue | E25: Product | F25: Enterprise | G25: West | H25: CUST10218 | J25: Identify loss across fact government sea upon. | K25: =IF(COUNTIF(Customers!A:A, H25)>0, "Valid", "Invalid") -> Valid | L25: =TEXT(B25,"m") -> 9 | M25: =TEXT(B25,"yyyy") -> 2023 | N25: =IF(D25="Revenue",C25,-ABS(C25)) -> 171433.19 | O25: =IF(D25="Revenue", C25, "") -> 171433.19 | P25: =IF(D25="Expense", ABS(C25), "") | Q25: =IF(O25="","", IF(OR(O25<EDA_Outlier_Analysis!$C$10, O25>EDA_Outlier_Analysis!$C$11), "Outlier", "Normal")) -> Normal | R25: =IF(P25="","", IF(OR(P25 < EDA_Outlier_Analysis!$F$7, P25 > EDA_Outlier_Analysis!$F$8), "Outlier", "Normal")) | S25: =IF(N25="","", IF(OR(N25 <EDA_Outlier_Analysis!$I$10, N25 > EDA_Outlier_Analysis!$I$11), "Outlier", "Normal")) -> Normal
A26: TRX100024 | B26: 44850 | C26: -60198.87 | D26: Expense | E26: Payroll | F26: Enterprise | G26: North | I26: VEND1058 | J26: Big fine cause full reality heart condition another. | K26: =IF(COUNTIF(Customers!A:A, H26)>0, "Valid", "Invalid") -> Invalid | L26: =TEXT(B26,"m") -> 10 | M26: =TEXT(B26,"yyyy") -> 2022 | N26: =IF(D26="Revenue",C26,-ABS(C26)) -> -60198.87 | O26: =IF(D26="Revenue", C26, "") | P26: =IF(D26="Expense", ABS(C26), "") -> 60198.87 | Q26: =IF(O26="","", IF(OR(O26<EDA_Outlier_Analysis!$C$10, O26>EDA_Outlier_Analysis!$C$11), "Outlier", "Normal")) | R26: =IF(P26="","", IF(OR(P26 < EDA_Outlier_Analysis!$F$7, P26 > EDA_Outlier_Analysis!$F$8), "Outlier", "Normal")) -> Outlier | S26: =IF(N26="","", IF(OR(N26 <EDA_Outlier_Analysis!$I$10, N26 > EDA_Outlier_Analysis!$I$11), "Outlier", "Normal")) -> Normal
A27: TRX100025 | B27: 45097 | C27: -40143.88 | D27: Expense | E27: Rent | F27: Retail | G27: West | I27: VEND1037 | J27: Good owner financial any result summer physical. | K27: =IF(COUNTIF(Customers!A:A, H27)>0, "Valid", "Invalid") -> Invalid | L27: =TEXT(B27,"m") -> 6 | M27: =TEXT(B27,"yyyy") -> 2023 | N27: =IF(D27="Revenue",C27,-ABS(C27)) -> -40143.88 | O27: =IF(D27="Revenue", C27, "") | P27: =IF(D27="Expense", ABS(C27), "") -> 40143.88 | Q27: =IF(O27="","", IF(OR(O27<EDA_Outlier_Analysis!$C$10, O27>EDA_Outlier_Analysis!$C$11), "Outlier", "Normal")) | R27: =IF(P27="","", IF(OR(P27 < EDA_Outlier_Analysis!$F$7, P27 > EDA_Outlier_Analysis!$F$8), "Outlier", "Normal")) -> Normal | S27: =IF(N27="","", IF(OR(N27 <EDA_Outlier_Analysis!$I$10, N27 > EDA_Outlier_Analysis!$I$11), "Outlier", "Normal")) -> Normal
A28: TRX100026 | B28: 45208 | C28: -38329 | D28: Expense | E28: Marketing | F28: Enterprise | G28: West | I28: VEND1049 | J28: Sport note decide who modern car knowledge. | K28: =IF(COUNTIF(Customers!A:A, H28)>0, "Valid", "Invalid") -> Invalid | L28: =TEXT(B28,"m") -> 10 | M28: =TEXT(B28,"yyyy") -> 2023 | N28: =IF(D28="Revenue",C28,-ABS(C28)) -> -38329 | O28: =IF(D28="Revenue", C28, "") | P28: =IF(D28="Expense", ABS(C28), "") -> 38329 | Q28: =IF(O28="","", IF(OR(O28<EDA_Outlier_Analysis!$C$10, O28>EDA_Outlier_Analysis!$C$11), "Outlier", "Normal")) | R28: =IF(P28="","", IF(OR(P28 < EDA_Outlier_Analysis!$F$7, P28 > EDA_Outlier_Analysis!$F$8), "Outlier", "Normal")) -> Normal | S28: =IF(N28="","", IF(OR(N28 <EDA_Outlier_Analysis!$I$10, N28 > EDA_Outlier_Analysis!$I$11), "Outlier", "Normal")) -> Normal
A29: TRX100027 | B29: 44901 | C29: 193475.45 | D29: Revenue | E29: Service | F29: Retail | G29: South | H29: CUST10146 | J29: Game step assume late home order morning to. | K29: =IF(COUNTIF(Customers!A:A, H29)>0, "Valid", "Invalid") -> Valid | L29: =TEXT(B29,"m") -> 12 | M29: =TEXT(B29,"yyyy") -> 2022 | N29: =IF(D29="Revenue",C29,-ABS(C29)) -> 193475.45 | O29: =IF(D29="Revenue", C29, "") -> 193475.45 | P29: =IF(D29="Expense", ABS(C29), "") | Q29: =IF(O29="","", IF(OR(O29<EDA_Outlier_Analysis!$C$10, O29>EDA_Outlier_Analysis!$C$11), "Outlier", "Normal")) -> Normal | R29: =IF(P29="","", IF(OR(P29 < EDA_Outlier_Analysis!$F$7, P29 > EDA_Outlier_Analysis!$F$8), "Outlier", "Normal")) | S29: =IF(N29="","", IF(OR(N29 <EDA_Outlier_Analysis!$I$10, N29 > EDA_Outlier_Analysis!$I$11), "Outlier", "Normal")) -> Normal
A30: TRX100028 | B30: 45002 | C30: 139672.98 | D30: Revenue | E30: Subscription | F30: Enterprise | G30: South | H30: CUST10074 | J30: Nature need environment operation country easy across choice. | K30: =IF(COUNTIF(Customers!A:A, H30)>0, "Valid", "Invalid") -> Valid | L30: =TEXT(B30,"m") -> 3 | M30: =TEXT(B30,"yyyy") -> 2023 | N30: =IF(D30="Revenue",C30,-ABS(C30)) -> 139672.98 | O30: =IF(D30="Revenue", C30, "") -> 139672.98 | P30: =IF(D30="Expense", ABS(C30), "") | Q30: =IF(O30="","", IF(OR(O30<EDA_Outlier_Analysis!$C$10, O30>EDA_Outlier_Analysis!$C$11), "Outlier", "Normal")) -> Normal | R30: =IF(P30="","", IF(OR(P30 < EDA_Outlier_Analysis!$F$7, P30 > EDA_Outlier_Analysis!$F$8), "Outlier", "Normal")) | S30: =IF(N30="","", IF(OR(N30 <EDA_Outlier_Analysis!$I$10, N30 > EDA_Outlier_Analysis!$I$11), "Outlier", "Normal")) -> Normal
A31: TRX100029 | B31: 45188 | C31: 198385.78 | D31: Revenue | E31: Subscription | F31: Enterprise | G31: North | H31: CUST10011 | J31: Scientist particularly include true listen happy. | K31: =IF(COUNTIF(Customers!A:A, H31)>0, "Valid", "Invalid") -> Valid | L31: =TEXT(B31,"m") -> 9 | M31: =TEXT(B31,"yyyy") -> 2023 | N31: =IF(D31="Revenue",C31,-ABS(C31)) -> 198385.78 | O31: =IF(D31="Revenue", C31, "") -> 198385.78 | P31: =IF(D31="Expense", ABS(C31), "") | Q31: =IF(O31="","", IF(OR(O31<EDA_Outlier_Analysis!$C$10, O31>EDA_Outlier_Analysis!$C$11), "Outlier", "Normal")) -> Normal | R31: =IF(P31="","", IF(OR(P31 < EDA_Outlier_Analysis!$F$7, P31 > EDA_Outlier_Analysis!$F$8), "Outlier", "Normal")) | S31: =IF(N31="","", IF(OR(N31 <EDA_Outlier_Analysis!$I$10, N31 > EDA_Outlier_Analysis!$I$11), "Outlier", "Normal")) -> Normal
A32: TRX100030 | B32: 44814 | C32: 137108.16 | D32: Revenue | E32: Service | F32: Enterprise | G32: East | H32: CUST10325 | J32: Citizen help never simple course. | K32: =IF(COUNTIF(Customers!A:A, H32)>0, "Valid", "Invalid") -> Valid | L32: =TEXT(B32,"m") -> 9 | M32: =TEXT(B32,"yyyy") -> 2022 | N32: =IF(D32="Revenue",C32,-ABS(C32)) -> 137108.16 | O32: =IF(D32="Revenue", C32, "") -> 137108.16 | P32: =IF(D32="Expense", ABS(C32), "") | Q32: =IF(O32="","", IF(OR(O32<EDA_Outlier_Analysis!$C$10, O32>EDA_Outlier_Analysis!$C$11), "Outlier", "Normal")) -> Normal | R32: =IF(P32="","", IF(OR(P32 < EDA_Outlier_Analysis!$F$7, P32 > EDA_Outlier_Analysis!$F$8), "Outlier", "Normal")) | S32: =IF(N32="","", IF(OR(N32 <EDA_Outlier_Analysis!$I$10, N32 > EDA_Outlier_Analysis!$I$11), "Outlier", "Normal")) -> Normal
A33: TRX100031 | B33: 44624 | C33: -44326.21 | D33: Expense | E33: Other | F33: Retail | G33: East | I33: VEND1053 | J33: Billion newspaper modern fine career somebody. | K33: =IF(COUNTIF(Customers!A:A, H33)>0, "Valid", "Invalid") -> Invalid | L33: =TEXT(B33,"m") -> 3 | M33: =TEXT(B33,"yyyy") -> 2022 | N33: =IF(D33="Revenue",C33,-ABS(C33)) -> -44326.21 | O33: =IF(D33="Revenue", C33, "") | P33: =IF(D33="Expense", ABS(C33), "") -> 44326.21 | Q33: =IF(O33="","", IF(OR(O33<EDA_Outlier_Analysis!$C$10, O33>EDA_Outlier_Analysis!$C$11), "Outlier", "Normal")) | R33: =IF(P33="","", IF(OR(P33 < EDA_Outlier_Analysis!$F$7, P33 > EDA_Outlier_Analysis!$F$8), "Outlier", "Normal")) -> Normal | S33: =IF(N33="","", IF(OR(N33 <EDA_Outlier_Analysis!$I$10, N33 > EDA_Outlier_Analysis!$I$11), "Outlier", "Normal")) -> Normal
A34: TRX100032 | B34: 44970 | C34: 162088.99 | D34: Revenue | E34: Service | F34: Enterprise | G34: North | H34: CUST10203 | J34: Wall campaign might anyone. | K34: =IF(COUNTIF(Customers!A:A, H34)>0, "Valid", "Invalid") -> Valid | L34: =TEXT(B34,"m") -> 2 | M34: =TEXT(B34,"yyyy") -> 2023 | N34: =IF(D34="Revenue",C34,-ABS(C34)) -> 162088.99 | O34: =IF(D34="Revenue", C34, "") -> 162088.99 | P34: =IF(D34="Expense", ABS(C34), "") | Q34: =IF(O34="","", IF(OR(O34<EDA_Outlier_Analysis!$C$10, O34>EDA_Outlier_Analysis!$C$11), "Outlier", "Normal")) -> Normal | R34: =IF(P34="","", IF(OR(P34 < EDA_Outlier_Analysis!$F$7, P34 > EDA_Outlier_Analysis!$F$8), "Outlier", "Normal")) | S34: =IF(N34="","", IF(OR(N34 <EDA_Outlier_Analysis!$I$10, N34 > EDA_Outlier_Analysis!$I$11), "Outlier", "Normal")) -> Normal
A35: TRX100033 | B35: 44847 | C35: 138103.68 | D35: Revenue | E35: Subscription | F35: Online | G35: North | H35: CUST10151 | J35: Could impact decide key. | K35: =IF(COUNTIF(Customers!A:A, H35)>0, "Valid", "Invalid") -> Valid | L35: =TEXT(B35,"m") -> 10 | M35: =TEXT(B35,"yyyy") -> 2022 | N35: =IF(D35="Revenue",C35,-ABS(C35)) -> 138103.68 | O35: =IF(D35="Revenue", C35, "") -> 138103.68 | P35: =IF(D35="Expense", ABS(C35), "") | Q35: =IF(O35="","", IF(OR(O35<EDA_Outlier_Analysis!$C$10, O35>EDA_Outlier_Analysis!$C$11), "Outlier", "Normal")) -> Normal | R35: =IF(P35="","", IF(OR(P35 < EDA_Outlier_Analysis!$F$7, P35 > EDA_Outlier_Analysis!$F$8), "Outlier", "Normal")) | S35: =IF(N35="","", IF(OR(N35 <EDA_Outlier_Analysis!$I$10, N35 > EDA_Outlier_Analysis!$I$11), "Outlier", "Normal")) -> Normal
A36: TRX100034 | B36: 44695 | C36: -10197.61 | D36: Expense | E36: Utilities | F36: Retail | G36: East | I36: VEND1014 | J36: Imagine must who discover since painting. | K36: =IF(COUNTIF(Customers!A:A, H36)>0, "Valid", "Invalid") -> Invalid | L36: =TEXT(B36,"m") -> 5 | M36: =TEXT(B36,"yyyy") -> 2022 | N36: =IF(D36="Revenue",C36,-ABS(C36)) -> -10197.61 | O36: =IF(D36="Revenue", C36, "") | P36: =IF(D36="Expense", ABS(C36), "") -> 10197.61 | Q36: =IF(O36="","", IF(OR(O36<EDA_Outlier_Analysis!$C$10, O36>EDA_Outlier_Analysis!$C$11), "Outlier", "Normal")) | R36: =IF(P36="","", IF(OR(P36 < EDA_Outlier_Analysis!$F$7, P36 > EDA_Outlier_Analysis!$F$8), "Outlier", "Normal")) -> Outlier | S36: =IF(N36="","", IF(OR(N36 <EDA_Outlier_Analysis!$I$10, N36 > EDA_Outlier_Analysis!$I$11), "Outlier", "Normal")) -> Normal
A37: TRX100035 | B37: 45145 | C37: -62926.94 | D37: Expense | E37: Marketing | F37: Retail | G37: West | I37: VEND1093 | J37: Training nor arrive. | K37: =IF(COUNTIF(Customers!A:A, H37)>0, "Valid", "Invalid") -> Invalid | L37: =TEXT(B37,"m") -> 8 | M37: =TEXT(B37,"yyyy") -> 2023 | N37: =IF(D37="Revenue",C37,-ABS(C37)) -> -62926.94 | O37: =IF(D37="Revenue", C37, "") | P37: =IF(D37="Expense", ABS(C37), "") -> 62926.94 | Q37: =IF(O37="","", IF(OR(O37<EDA_Outlier_Analysis!$C$10, O37>EDA_Outlier_Analysis!$C$11), "Outlier", "Normal")) | R37: =IF(P37="","", IF(OR(P37 < EDA_Outlier_Analysis!$F$7, P37 > EDA_Outlier_Analysis!$F$8), "Outlier", "Normal")) -> Outlier | S37: =IF(N37="","", IF(OR(N37 <EDA_Outlier_Analysis!$I$10, N37 > EDA_Outlier_Analysis!$I$11), "Outlier", "Normal")) -> Normal
A38: TRX100036 | B38: 45195 | C38: 144593.87 | D38: Revenue | E38: Service | F38: Enterprise | G38: East | H38: CUST10086 | J38: Field some arrive society everybody guy public. | K38: =IF(COUNTIF(Customers!A:A, H38)>0, "Valid", "Invalid") -> Valid | L38: =TEXT(B38,"m") -> 9 | M38: =TEXT(B38,"yyyy") -> 2023 | N38: =IF(D38="Revenue",C38,-ABS(C38)) -> 144593.87 | O38: =IF(D38="Revenue", C38, "") -> 144593.87 | P38: =IF(D38="Expense", ABS(C38), "") | Q38: =IF(O38="","", IF(OR(O38<EDA_Outlier_Analysis!$C$10, O38>EDA_Outlier_Analysis!$C$11), "Outlier", "Normal")) -> Normal | R38: =IF(P38="","", IF(OR(P38 < EDA_Outlier_Analysis!$F$7, P38 > EDA_Outlier_Analysis!$F$8), "Outlier", "Normal")) | S38: =IF(N38="","", IF(OR(N38 <EDA_Outlier_Analysis!$I$10, N38 > EDA_Outlier_Analysis!$I$11), "Outlier", "Normal")) -> Normal
A39: TRX100037 | B39: 44595 | C39: 38814.58 | D39: Revenue | E39: Product | F39: Retail | G39: North | H39: CUST10013 | J39: Order agreement mind everything. | K39: =IF(COUNTIF(Customers!A:A, H39)>0, "Valid", "Invalid") -> Valid | L39: =TEXT(B39,"m") -> 2 | M39: =TEXT(B39,"yyyy") -> 2022 | N39: =IF(D39="Revenue",C39,-ABS(C39)) -> 38814.58 | O39: =IF(D39="Revenue", C39, "") -> 38814.58 | P39: =IF(D39="Expense", ABS(C39), "") | Q39: =IF(O39="","", IF(OR(O39<EDA_Outlier_Analysis!$C$10, O39>EDA_Outlier_Analysis!$C$11), "Outlier", "Normal")) -> Normal | R39: =IF(P39="","", IF(OR(P39 < EDA_Outlier_Analysis!$F$7, P39 > EDA_Outlier_Analysis!$F$8), "Outlier", "Normal")) | S39: =IF(N39="","", IF(OR(N39 <EDA_Outlier_Analysis!$I$10, N39 > EDA_Outlier_Analysis!$I$11), "Outlier", "Normal")) -> Normal
A40: TRX100038 | B40: 44983 | C40: -36977.97 | D40: Expense | E40: Rent | F40: Online | G40: East | I40: VEND1082 | J40: Watch would miss interview water trouble. | K40: =IF(COUNTIF(Customers!A:A, H40)>0, "Valid", "Invalid") -> Invalid | L40: =TEXT(B40,"m") -> 2 | M40: =TEXT(B40,"yyyy") -> 2023 | N40: =IF(D40="Revenue",C40,-ABS(C40)) -> -36977.97 | O40: =IF(D40="Revenue", C40, "") | P40: =IF(D40="Expense", ABS(C40), "") -> 36977.97 | Q40: =IF(O40="","", IF(OR(O40<EDA_Outlier_Analysis!$C$10, O40>EDA_Outlier_Analysis!$C$11), "Outlier", "Normal")) | R40: =IF(P40="","", IF(OR(P40 < EDA_Outlier_Analysis!$F$7, P40 > EDA_Outlier_Analysis!$F$8), "Outlier", "Normal")) -> Normal | S40: =IF(N40="","", IF(OR(N40 <EDA_Outlier_Analysis!$I$10, N40 > EDA_Outlier_Analysis!$I$11), "Outlier", "Normal")) -> Normal
A41: TRX100039 | B41: 44914 | C41: -18304.84 | D41: Expense | E41: Payroll | F41: Enterprise | G41: East | I41: VEND1106 | J41: Save in thing model. | K41: =IF(COUNTIF(Customers!A:A, H41)>0, "Valid", "Invalid") -> Invalid | L41: =TEXT(B41,"m") -> 12 | M41: =TEXT(B41,"yyyy") -> 2022 | N41: =IF(D41="Revenue",C41,-ABS(C41)) -> -18304.84 | O41: =IF(D41="Revenue", C41, "") | P41: =IF(D41="Expense", ABS(C41), "") -> 18304.84 | Q41: =IF(O41="","", IF(OR(O41<EDA_Outlier_Analysis!$C$10, O41>EDA_Outlier_Analysis!$C$11), "Outlier", "Normal")) | R41: =IF(P41="","", IF(OR(P41 < EDA_Outlier_Analysis!$F$7, P41 > EDA_Outlier_Analysis!$F$8), "Outlier", "Normal")) -> Outlier | S41: =IF(N41="","", IF(OR(N41 <EDA_Outlier_Analysis!$I$10, N41 > EDA_Outlier_Analysis!$I$11), "Outlier", "Normal")) -> Normal
A42: TRX100040 | B42: 45228 | C42: 248459.88 | D42: Revenue | E42: Subscription | F42: Online | G42: East | H42: CUST10022 | J42: Defense argue help someone action throw. | K42: =IF(COUNTIF(Customers!A:A, H42)>0, "Valid", "Invalid") -> Valid | L42: =TEXT(B42,"m") -> 10 | M42: =TEXT(B42,"yyyy") -> 2023 | N42: =IF(D42="Revenue",C42,-ABS(C42)) -> 248459.88 | O42: =IF(D42="Revenue", C42, "") -> 248459.88 | P42: =IF(D42="Expense", ABS(C42), "") | Q42: =IF(O42="","", IF(OR(O42<EDA_Outlier_Analysis!$C$10, O42>EDA_Outlier_Analysis!$C$11), "Outlier", "Normal")) -> Normal | R42: =IF(P42="","", IF(OR(P42 < EDA_Outlier_Analysis!$F$7, P42 > EDA_Outlier_Analysis!$F$8), "Outlier", "Normal")) | S42: =IF(N42="","", IF(OR(N42 <EDA_Outlier_Analysis!$I$10, N42 > EDA_Outlier_Analysis!$I$11), "Outlier", "Normal")) -> Normal
A43: TRX100041 | B43: 44838 | C43: 120099.72 | D43: Revenue | E43: Product | F43: Online | G43: East | H43: CUST10128 | J43: Reduce suddenly against ball medical. | K43: =IF(COUNTIF(Customers!A:A, H43)>0, "Valid", "Invalid") -> Valid | L43: =TEXT(B43,"m") -> 10 | M43: =TEXT(B43,"yyyy") -> 2022 | N43: =IF(D43="Revenue",C43,-ABS(C43)) -> 120099.72 | O43: =IF(D43="Revenue", C43, "") -> 120099.72 | P43: =IF(D43="Expense", ABS(C43), "") | Q43: =IF(O43="","", IF(OR(O43<EDA_Outlier_Analysis!$C$10, O43>EDA_Outlier_Analysis!$C$11), "Outlier", "Normal")) -> Normal | R43: =IF(P43="","", IF(OR(P43 < EDA_Outlier_Analysis!$F$7, P43 > EDA_Outlier_Analysis!$F$8), "Outlier", "Normal")) | S43: =IF(N43="","", IF(OR(N43 <EDA_Outlier_Analysis!$I$10, N43 > EDA_Outlier_Analysis!$I$11), "Outlier", "Normal")) -> Normal
A44: TRX100042 | B44: 44888 | C44: -39571.02 | D44: Expense | E44: Other | F44: Online | G44: South | I44: VEND1063 | J44: Far make skill lose audience art. | K44: =IF(COUNTIF(Customers!A:A, H44)>0, "Valid", "Invalid") -> Invalid | L44: =TEXT(B44,"m") -> 11 | M44: =TEXT(B44,"yyyy") -> 2022 | N44: =IF(D44="Revenue",C44,-ABS(C44)) -> -39571.02 | O44: =IF(D44="Revenue", C44, "") | P44: =IF(D44="Expense", ABS(C44), "") -> 39571.02 | Q44: =IF(O44="","", IF(OR(O44<EDA_Outlier_Analysis!$C$10, O44>EDA_Outlier_Analysis!$C$11), "Outlier", "Normal")) | R44: =IF(P44="","", IF(OR(P44 < EDA_Outlier_Analysis!$F$7, P44 > EDA_Outlier_Analysis!$F$8), "Outlier", "Normal")) -> Normal | S44: =IF(N44="","", IF(OR(N44 <EDA_Outlier_Analysis!$I$10, N44 > EDA_Outlier_Analysis!$I$11), "Outlier", "Normal")) -> Normal
A45: TRX100043 | B45: 45033 | C45: 79909.54 | D45: Revenue | E45: Subscription | F45: Retail | G45: East | H45: CUST10251 | J45: Tax north line it fund describe. | K45: =IF(COUNTIF(Customers!A:A, H45)>0, "Valid", "Invalid") -> Valid | L45: =TEXT(B45,"m") -> 4 | M45: =TEXT(B45,"yyyy") -> 2023 | N45: =IF(D45="Revenue",C45,-ABS(C45)) -> 79909.54 | O45: =IF(D45="Revenue", C45, "") -> 79909.54 | P45: =IF(D45="Expense", ABS(C45), "") | Q45: =IF(O45="","", IF(OR(O45<EDA_Outlier_Analysis!$C$10, O45>EDA_Outlier_Analysis!$C$11), "Outlier", "Normal")) -> Normal | R45: =IF(P45="","", IF(OR(P45 < EDA_Outlier_Analysis!$F$7, P45 > EDA_Outlier_Analysis!$F$8), "Outlier", "Normal")) | S45: =IF(N45="","", IF(OR(N45 <EDA_Outlier_Analysis!$I$10, N45 > EDA_Outlier_Analysis!$I$11), "Outlier", "Normal")) -> Normal
A46: TRX100044 | B46: 44977 | C46: -50444.36 | D46: Expense | E46: Other | F46: Enterprise | G46: North | I46: VEND1020 | J46: Follow put campaign lose summer lot if others. | K46: =IF(COUNTIF(Customers!A:A, H46)>0, "Valid", "Invalid") -> Invalid | L46: =TEXT(B46,"m") -> 2 | M46: =TEXT(B46,"yyyy") -> 2023 | N46: =IF(D46="Revenue",C46,-ABS(C46)) -> -50444.36 | O46: =IF(D46="Revenue", C46, "") | P46: =IF(D46="Expense", ABS(C46), "") -> 50444.36 | Q46: =IF(O46="","", IF(OR(O46<EDA_Outlier_Analysis!$C$10, O46>EDA_Outlier_Analysis!$C$11), "Outlier", "Normal")) | R46: =IF(P46="","", IF(OR(P46 < EDA_Outlier_Analysis!$F$7, P46 > EDA_Outlier_Analysis!$F$8), "Outlier", "Normal")) -> Normal | S46: =IF(N46="","", IF(OR(N46 <EDA_Outlier_Analysis!$I$10, N46 > EDA_Outlier_Analysis!$I$11), "Outlier", "Normal")) -> Normal
A47: TRX100045 | B47: 44879 | C47: -22716.39 | D47: Expense | E47: Supplies | F47: Retail | G47: East | I47: VEND1062 | J47: Structure have effect. | K47: =IF(COUNTIF(Customers!A:A, H47)>0, "Valid", "Invalid") -> Invalid | L47: =TEXT(B47,"m") -> 11 | M47: =TEXT(B47,"yyyy") -> 2022 | N47: =IF(D47="Revenue",C47,-ABS(C47)) -> -22716.39 | O47: =IF(D47="Revenue", C47, "") | P47: =IF(D47="Expense", ABS(C47), "") -> 22716.39 | Q47: =IF(O47="","", IF(OR(O47<EDA_Outlier_Analysis!$C$10, O47>EDA_Outlier_Analysis!$C$11), "Outlier", "Normal")) | R47: =IF(P47="","", IF(OR(P47 < EDA_Outlier_Analysis!$F$7, P47 > EDA_Outlier_Analysis!$F$8), "Outlier", "Normal")) -> Outlier | S47: =IF(N47="","", IF(OR(N47 <EDA_Outlier_Analysis!$I$10, N47 > EDA_Outlier_Analysis!$I$11), "Outlier", "Normal")) -> Normal
A48: TRX100046 | B48: 44934 | C48: -14936.32 | D48: Expense | E48: Marketing | F48: Online | G48: East | I48: VEND1025 | J48: Second get its since return. | K48: =IF(COUNTIF(Customers!A:A, H48)>0, "Valid", "Invalid") -> Invalid | L48: =TEXT(B48,"m") -> 1 | M48: =TEXT(B48,"yyyy") -> 2023 | N48: =IF(D48="Revenue",C48,-ABS(C48)) -> -14936.32 | O48: =IF(D48="Revenue", C48, "") | P48: =IF(D48="Expense", ABS(C48), "") -> 14936.32 | Q48: =IF(O48="","", IF(OR(O48<EDA_Outlier_Analysis!$C$10, O48>EDA_Outlier_Analysis!$C$11), "Outlier", "Normal")) | R48: =IF(P48="","", IF(OR(P48 < EDA_Outlier_Analysis!$F$7, P48 > EDA_Outlier_Analysis!$F$8), "Outlier", "Normal")) -> Outlier | S48: =IF(N48="","", IF(OR(N48 <EDA_Outlier_Analysis!$I$10, N48 > EDA_Outlier_Analysis!$I$11), "Outlier", "Normal")) -> Normal
A49: TRX100047 | B49: 45199 | C49: 141946.92 | D49: Revenue | E49: Service | F49: Retail | G49: West | H49: CUST10342 | J49: Then section each support majority. | K49: =IF(COUNTIF(Customers!A:A, H49)>0, "Valid", "Invalid") -> Valid | L49: =TEXT(B49,"m") -> 9 | M49: =TEXT(B49,"yyyy") -> 2023 | N49: =IF(D49="Revenue",C49,-ABS(C49)) -> 141946.92 | O49: =IF(D49="Revenue", C49, "") -> 141946.92 | P49: =IF(D49="Expense", ABS(C49), "") | Q49: =IF(O49="","", IF(OR(O49<EDA_Outlier_Analysis!$C$10, O49>EDA_Outlier_Analysis!$C$11), "Outlier", "Normal")) -> Normal | R49: =IF(P49="","", IF(OR(P49 < EDA_Outlier_Analysis!$F$7, P49 > EDA_Outlier_Analysis!$F$8), "Outlier", "Normal")) | S49: =IF(N49="","", IF(OR(N49 <EDA_Outlier_Analysis!$I$10, N49 > EDA_Outlier_Analysis!$I$11), "Outlier", "Normal")) -> Normal
A50: TRX100048 | B50: 45265 | C50: -28844.76 | D50: Expense | E50: Supplies | F50: Online | G50: West | I50: VEND1060 | J50: Where keep leader computer father brother a give. | K50: =IF(COUNTIF(Customers!A:A, H50)>0, "Valid", "Invalid") -> Invalid | L50: =TEXT(B50,"m") -> 12 | M50: =TEXT(B50,"yyyy") -> 2023 | N50: =IF(D50="Revenue",C50,-ABS(C50)) -> -28844.76 | O50: =IF(D50="Revenue", C50, "") | P50: =IF(D50="Expense", ABS(C50), "") -> 28844.76 | Q50: =IF(O50="","", IF(OR(O50<EDA_Outlier_Analysis!$C$10, O50>EDA_Outlier_Analysis!$C$11), "Outlier", "Normal")) | R50: =IF(P50="","", IF(OR(P50 < EDA_Outlier_Analysis!$F$7, P50 > EDA_Outlier_Analysis!$F$8), "Outlier", "Normal")) -> Normal | S50: =IF(N50="","", IF(OR(N50 <EDA_Outlier_Analysis!$I$10, N50 > EDA_Outlier_Analysis!$I$11), "Outlier", "Normal")) -> Normal
A51: TRX100049 | B51: 44782 | C51: -66244 | D51: Expense | E51: Supplies | F51: Enterprise | G51: North | I51: VEND1089 | J51: Big itself serious. | K51: =IF(COUNTIF(Customers!A:A, H51)>0, "Valid", "Invalid") -> Invalid | L51: =TEXT(B51,"m") -> 8 | M51: =TEXT(B51,"yyyy") -> 2022 | N51: =IF(D51="Revenue",C51,-ABS(C51)) -> -66244 | O51: =IF(D51="Revenue", C51, "") | P51: =IF(D51="Expense", ABS(C51), "") -> 66244 | Q51: =IF(O51="","", IF(OR(O51<EDA_Outlier_Analysis!$C$10, O51>EDA_Outlier_Analysis!$C$11), "Outlier", "Normal")) | R51: =IF(P51="","", IF(OR(P51 < EDA_Outlier_Analysis!$F$7, P51 > EDA_Outlier_Analysis!$F$8), "Outlier", "Normal")) -> Outlier | S51: =IF(N51="","", IF(OR(N51 <EDA_Outlier_Analysis!$I$10, N51 > EDA_Outlier_Analysis!$I$11), "Outlier", "Normal")) -> Normal
A52: TRX100050 | B52: 45018 | C52: 15704.88 | D52: Asset | E52: Asset | F52: Enterprise | G52: East | J52: Test fill perform voice. | K52: =IF(COUNTIF(Customers!A:A, H52)>0, "Valid", "Invalid") -> Invalid | L52: =TEXT(B52,"m") -> 4 | M52: =TEXT(B52,"yyyy") -> 2023 | N52: =IF(D52="Revenue",C52,-ABS(C52)) -> -15704.88 | O52: =IF(D52="Revenue", C52, "") | P52: =IF(D52="Expense", ABS(C52), "") | Q52: =IF(O52="","", IF(OR(O52<EDA_Outlier_Analysis!$C$10, O52>EDA_Outlier_Analysis!$C$11), "Outlier", "Normal")) | R52: =IF(P52="","", IF(OR(P52 < EDA_Outlier_Analysis!$F$7, P52 > EDA_Outlier_Analysis!$F$8), "Outlier", "Normal")) | S52: =IF(N52="","", IF(OR(N52 <EDA_Outlier_Analysis!$I$10, N52 > EDA_Outlier_Analysis!$I$11), "Outlier", "Normal")) -> Normal
A53: TRX100051 | B53: 44822 | C53: 209846.71 | D53: Revenue | E53: Subscription | F53: Retail | G53: South | H53: CUST10190 | J53: School common voice itself. | K53: =IF(COUNTIF(Customers!A:A, H53)>0, "Valid", "Invalid") -> Valid | L53: =TEXT(B53,"m") -> 9 | M53: =TEXT(B53,"yyyy") -> 2022 | N53: =IF(D53="Revenue",C53,-ABS(C53)) -> 209846.71 | O53: =IF(D53="Revenue", C53, "") -> 209846.71 | P53: =IF(D53="Expense", ABS(C53), "") | Q53: =IF(O53="","", IF(OR(O53<EDA_Outlier_Analysis!$C$10, O53>EDA_Outlier_Analysis!$C$11), "Outlier", "Normal")) -> Normal | R53: =IF(P53="","", IF(OR(P53 < EDA_Outlier_Analysis!$F$7, P53 > EDA_Outlier_Analysis!$F$8), "Outlier", "Normal")) | S53: =IF(N53="","", IF(OR(N53 <EDA_Outlier_Analysis!$I$10, N53 > EDA_Outlier_Analysis!$I$11), "Outlier", "Normal")) -> Normal
A54: TRX100052 | B54: 44728 | C54: -45798.81 | D54: Expense | E54: Marketing | F54: Enterprise | G54: East | I54: VEND1011 | J54: Majority early special record sit scene price. | K54: =IF(COUNTIF(Customers!A:A, H54)>0, "Valid", "Invalid") -> Invalid | L54: =TEXT(B54,"m") -> 6 | M54: =TEXT(B54,"yyyy") -> 2022 | N54: =IF(D54="Revenue",C54,-ABS(C54)) -> -45798.81 | O54: =IF(D54="Revenue", C54, "") | P54: =IF(D54="Expense", ABS(C54), "") -> 45798.81 | Q54: =IF(O54="","", IF(OR(O54<EDA_Outlier_Analysis!$C$10, O54>EDA_Outlier_Analysis!$C$11), "Outlier", "Normal")) | R54: =IF(P54="","", IF(OR(P54 < EDA_Outlier_Analysis!$F$7, P54 > EDA_Outlier_Analysis!$F$8), "Outlier", "Normal")) -> Normal | S54: =IF(N54="","", IF(OR(N54 <EDA_Outlier_Analysis!$I$10, N54 > EDA_Outlier_Analysis!$I$11), "Outlier", "Normal")) -> Normal
A55: TRX100053 | B55: 44687 | C55: -22712.23 | D55: Expense | E55: Payroll | F55: Enterprise | G55: North | I55: VEND1079 | J55: Daughter training suffer miss money. | K55: =IF(COUNTIF(Customers!A:A, H55)>0, "Valid", "Invalid") -> Invalid | L55: =TEXT(B55,"m") -> 5 | M55: =TEXT(B55,"yyyy") -> 2022 | N55: =IF(D55="Revenue",C55,-ABS(C55)) -> -22712.23 | O55: =IF(D55="Revenue", C55, "") | P55: =IF(D55="Expense", ABS(C55), "") -> 22712.23 | Q55: =IF(O55="","", IF(OR(O55<EDA_Outlier_Analysis!$C$10, O55>EDA_Outlier_Analysis!$C$11), "Outlier", "Normal")) | R55: =IF(P55="","", IF(OR(P55 < EDA_Outlier_Analysis!$F$7, P55 > EDA_Outlier_Analysis!$F$8), "Outlier", "Normal")) -> Outlier | S55: =IF(N55="","", IF(OR(N55 <EDA_Outlier_Analysis!$I$10, N55 > EDA_Outlier_Analysis!$I$11), "Outlier", "Normal")) -> Normal
A56: TRX100054 | B56: 44881 | C56: -51925.51 | D56: Expense | E56: Other | F56: Online | G56: East | I56: VEND1098 | J56: Including measure leave road leg mention. | K56: =IF(COUNTIF(Customers!A:A, H56)>0, "Valid", "Invalid") -> Invalid | L56: =TEXT(B56,"m") -> 11 | M56: =TEXT(B56,"yyyy") -> 2022 | N56: =IF(D56="Revenue",C56,-ABS(C56)) -> -51925.51 | O56: =IF(D56="Revenue", C56, "") | P56: =IF(D56="Expense", ABS(C56), "") -> 51925.51 | Q56: =IF(O56="","", IF(OR(O56<EDA_Outlier_Analysis!$C$10, O56>EDA_Outlier_Analysis!$C$11), "Outlier", "Normal")) | R56: =IF(P56="","", IF(OR(P56 < EDA_Outlier_Analysis!$F$7, P56 > EDA_Outlier_Analysis!$F$8), "Outlier", "Normal")) -> Normal | S56: =IF(N56="","", IF(OR(N56 <EDA_Outlier_Analysis!$I$10, N56 > EDA_Outlier_Analysis!$I$11), "Outlier", "Normal")) -> Normal
A57: TRX100055 | B57: 44960 | C57: -42768.16 | D57: Expense | E57: Rent | F57: Online | G57: North | I57: VEND1082 | J57: Technology far reach thought probably cover increase. | K57: =IF(COUNTIF(Customers!A:A, H57)>0, "Valid", "Invalid") -> Invalid | L57: =TEXT(B57,"m") -> 2 | M57: =TEXT(B57,"yyyy") -> 2023 | N57: =IF(D57="Revenue",C57,-ABS(C57)) -> -42768.16 | O57: =IF(D57="Revenue", C57, "") | P57: =IF(D57="Expense", ABS(C57), "") -> 42768.16 | Q57: =IF(O57="","", IF(OR(O57<EDA_Outlier_Analysis!$C$10, O57>EDA_Outlier_Analysis!$C$11), "Outlier", "Normal")) | R57: =IF(P57="","", IF(OR(P57 < EDA_Outlier_Analysis!$F$7, P57 > EDA_Outlier_Analysis!$F$8), "Outlier", "Normal")) -> Normal | S57: =IF(N57="","", IF(OR(N57 <EDA_Outlier_Analysis!$I$10, N57 > EDA_Outlier_Analysis!$I$11), "Outlier", "Normal")) -> Normal
A58: TRX100056 | B58: 44655 | C58: -22339.95 | D58: Expense | E58: Marketing | F58: Retail | G58: East | I58: VEND1001 | J58: Play prepare red goal. | K58: =IF(COUNTIF(Customers!A:A, H58)>0, "Valid", "Invalid") -> Invalid | L58: =TEXT(B58,"m") -> 4 | M58: =TEXT(B58,"yyyy") -> 2022 | N58: =IF(D58="Revenue",C58,-ABS(C58)) -> -22339.95 | O58: =IF(D58="Revenue", C58, "") | P58: =IF(D58="Expense", ABS(C58), "") -> 22339.95 | Q58: =IF(O58="","", IF(OR(O58<EDA_Outlier_Analysis!$C$10, O58>EDA_Outlier_Analysis!$C$11), "Outlier", "Normal")) | R58: =IF(P58="","", IF(OR(P58 < EDA_Outlier_Analysis!$F$7, P58 > EDA_Outlier_Analysis!$F$8), "Outlier", "Normal")) -> Outlier | S58: =IF(N58="","", IF(OR(N58 <EDA_Outlier_Analysis!$I$10, N58 > EDA_Outlier_Analysis!$I$11), "Outlier", "Normal")) -> Normal
A59: TRX100057 | B59: 44995 | C59: -43856.82 | D59: Expense | E59: Utilities | F59: Enterprise | G59: West | I59: VEND1042 | J59: Hard this despite certain they both provide machine. | K59: =IF(COUNTIF(Customers!A:A, H59)>0, "Valid", "Invalid") -> Invalid | L59: =TEXT(B59,"m") -> 3 | M59: =TEXT(B59,"yyyy") -> 2023 | N59: =IF(D59="Revenue",C59,-ABS(C59)) -> -43856.82 | O59: =IF(D59="Revenue", C59, "") | P59: =IF(D59="Expense", ABS(C59), "") -> 43856.82 | Q59: =IF(O59="","", IF(OR(O59<EDA_Outlier_Analysis!$C$10, O59>EDA_Outlier_Analysis!$C$11), "Outlier", "Normal")) | R59: =IF(P59="","", IF(OR(P59 < EDA_Outlier_Analysis!$F$7, P59 > EDA_Outlier_Analysis!$F$8), "Outlier", "Normal")) -> Normal | S59: =IF(N59="","", IF(OR(N59 <EDA_Outlier_Analysis!$I$10, N59 > EDA_Outlier_Analysis!$I$11), "Outlier", "Normal")) -> Normal
A60: TRX100058 | B60: 44730 | C60: 86224.06 | D60: Revenue | E60: Product | F60: Retail | G60: East | H60: CUST10151 | J60: Summer everyone his magazine six value week. | K60: =IF(COUNTIF(Customers!A:A, H60)>0, "Valid", "Invalid") -> Valid | L60: =TEXT(B60,"m") -> 6 | M60: =TEXT(B60,"yyyy") -> 2022 | N60: =IF(D60="Revenue",C60,-ABS(C60)) -> 86224.06 | O60: =IF(D60="Revenue", C60, "") -> 86224.06 | P60: =IF(D60="Expense", ABS(C60), "") | Q60: =IF(O60="","", IF(OR(O60<EDA_Outlier_Analysis!$C$10, O60>EDA_Outlier_Analysis!$C$11), "Outlier", "Normal")) -> Normal | R60: =IF(P60="","", IF(OR(P60 < EDA_Outlier_Analysis!$F$7, P60 > EDA_Outlier_Analysis!$F$8), "Outlier", "Normal")) | S60: =IF(N60="","", IF(OR(N60 <EDA_Outlier_Analysis!$I$10, N60 > EDA_Outlier_Analysis!$I$11), "Outlier", "Normal")) -> Normal
A61: TRX100059 | B61: 44818 | C61: 196305.77 | D61: Revenue | E61: Service | F61: Enterprise | G61: West | H61: CUST10016 | J61: Pm like matter price personal for. | K61: =IF(COUNTIF(Customers!A:A, H61)>0, "Valid", "Invalid") -> Valid | L61: =TEXT(B61,"m") -> 9 | M61: =TEXT(B61,"yyyy") -> 2022 | N61: =IF(D61="Revenue",C61,-ABS(C61)) -> 196305.77 | O61: =IF(D61="Revenue", C61, "") -> 196305.77 | P61: =IF(D61="Expense", ABS(C61), "") | Q61: =IF(O61="","", IF(OR(O61<EDA_Outlier_Analysis!$C$10, O61>EDA_Outlier_Analysis!$C$11), "Outlier", "Normal")) -> Normal | R61: =IF(P61="","", IF(OR(P61 < EDA_Outlier_Analysis!$F$7, P61 > EDA_Outlier_Analysis!$F$8), "Outlier", "Normal")) | S61: =IF(N61="","", IF(OR(N61 <EDA_Outlier_Analysis!$I$10, N61 > EDA_Outlier_Analysis!$I$11), "Outlier", "Normal")) -> Normal
A62: TRX100060 | B62: 45271 | C62: 144148.9 | D62: Revenue | E62: Product | F62: Online | G62: South | H62: CUST10049 | J62: True shoulder away. | K62: =IF(COUNTIF(Customers!A:A, H62)>0, "Valid", "Invalid") -> Valid | L62: =TEXT(B62,"m") -> 12 | M62: =TEXT(B62,"yyyy") -> 2023 | N62: =IF(D62="Revenue",C62,-ABS(C62)) -> 144148.9 | O62: =IF(D62="Revenue", C62, "") -> 144148.9 | P62: =IF(D62="Expense", ABS(C62), "") | Q62: =IF(O62="","", IF(OR(O62<EDA_Outlier_Analysis!$C$10, O62>EDA_Outlier_Analysis!$C$11), "Outlier", "Normal")) -> Normal | R62: =IF(P62="","", IF(OR(P62 < EDA_Outlier_Analysis!$F$7, P62 > EDA_Outlier_Analysis!$F$8), "Outlier", "Normal")) | S62: =IF(N62="","", IF(OR(N62 <EDA_Outlier_Analysis!$I$10, N62 > EDA_Outlier_Analysis!$I$11), "Outlier", "Normal")) -> Normal
A63: TRX100061 | B63: 44872 | C63: 161193.89 | D63: Revenue | E63: Product | F63: Online | G63: South | H63: CUST10129 | J63: Page truth although under for water analysis. | K63: =IF(COUNTIF(Customers!A:A, H63)>0, "Valid", "Invalid") -> Valid | L63: =TEXT(B63,"m") -> 11 | M63: =TEXT(B63,"yyyy") -> 2022 | N63: =IF(D63="Revenue",C63,-ABS(C63)) -> 161193.89 | O63: =IF(D63="Revenue", C63, "") -> 161193.89 | P63: =IF(D63="Expense", ABS(C63), "") | Q63: =IF(O63="","", IF(OR(O63<EDA_Outlier_Analysis!$C$10, O63>EDA_Outlier_Analysis!$C$11), "Outlier", "Normal")) -> Normal | R63: =IF(P63="","", IF(OR(P63 < EDA_Outlier_Analysis!$F$7, P63 > EDA_Outlier_Analysis!$F$8), "Outlier", "Normal")) | S63: =IF(N63="","", IF(OR(N63 <EDA_Outlier_Analysis!$I$10, N63 > EDA_Outlier_Analysis!$I$11), "Outlier", "Normal")) -> Normal
A64: TRX100062 | B64: 44808 | C64: 157413.67 | D64: Revenue | E64: Service | F64: Online | G64: West | H64: CUST10183 | J64: Early choice speech follow fund measure. | K64: =IF(COUNTIF(Customers!A:A, H64)>0, "Valid", "Invalid") -> Valid | L64: =TEXT(B64,"m") -> 9 | M64: =TEXT(B64,"yyyy") -> 2022 | N64: =IF(D64="Revenue",C64,-ABS(C64)) -> 157413.67 | O64: =IF(D64="Revenue", C64, "") -> 157413.67 | P64: =IF(D64="Expense", ABS(C64), "") | Q64: =IF(O64="","", IF(OR(O64<EDA_Outlier_Analysis!$C$10, O64>EDA_Outlier_Analysis!$C$11), "Outlier", "Normal")) -> Normal | R64: =IF(P64="","", IF(OR(P64 < EDA_Outlier_Analysis!$F$7, P64 > EDA_Outlier_Analysis!$F$8), "Outlier", "Normal")) | S64: =IF(N64="","", IF(OR(N64 <EDA_Outlier_Analysis!$I$10, N64 > EDA_Outlier_Analysis!$I$11), "Outlier", "Normal")) -> Normal
A65: TRX100063 | B65: 44583 | C65: 113690.25 | D65: Revenue | E65: Subscription | F65: Enterprise | G65: West | H65: CUST10348 | J65: Same whether interesting half Republican. | K65: =IF(COUNTIF(Customers!A:A, H65)>0, "Valid", "Invalid") -> Valid | L65: =TEXT(B65,"m") -> 1 | M65: =TEXT(B65,"yyyy") -> 2022 | N65: =IF(D65="Revenue",C65,-ABS(C65)) -> 113690.25 | O65: =IF(D65="Revenue", C65, "") -> 113690.25 | P65: =IF(D65="Expense", ABS(C65), "") | Q65: =IF(O65="","", IF(OR(O65<EDA_Outlier_Analysis!$C$10, O65>EDA_Outlier_Analysis!$C$11), "Outlier", "Normal")) -> Normal | R65: =IF(P65="","", IF(OR(P65 < EDA_Outlier_Analysis!$F$7, P65 > EDA_Outlier_Analysis!$F$8), "Outlier", "Normal")) | S65: =IF(N65="","", IF(OR(N65 <EDA_Outlier_Analysis!$I$10, N65 > EDA_Outlier_Analysis!$I$11), "Outlier", "Normal")) -> Normal
A66: TRX100064 | B66: 45152 | C66: 194267.47 | D66: Revenue | E66: Subscription | F66: Online | G66: East | H66: CUST10075 | J66: Half toward his. | K66: =IF(COUNTIF(Customers!A:A, H66)>0, "Valid", "Invalid") -> Valid | L66: =TEXT(B66,"m") -> 8 | M66: =TEXT(B66,"yyyy") -> 2023 | N66: =IF(D66="Revenue",C66,-ABS(C66)) -> 194267.47 | O66: =IF(D66="Revenue", C66, "") -> 194267.47 | P66: =IF(D66="Expense", ABS(C66), "") | Q66: =IF(O66="","", IF(OR(O66<EDA_Outlier_Analysis!$C$10, O66>EDA_Outlier_Analysis!$C$11), "Outlier", "Normal")) -> Normal | R66: =IF(P66="","", IF(OR(P66 < EDA_Outlier_Analysis!$F$7, P66 > EDA_Outlier_Analysis!$F$8), "Outlier", "Normal")) | S66: =IF(N66="","", IF(OR(N66 <EDA_Outlier_Analysis!$I$10, N66 > EDA_Outlier_Analysis!$I$11), "Outlier", "Normal")) -> Normal
A67: TRX100065 | B67: 45018 | C67: -53590.9 | D67: Expense | E67: Marketing | F67: Enterprise | G67: South | I67: VEND1107 | J67: Source learn expect show. | K67: =IF(COUNTIF(Customers!A:A, H67)>0, "Valid", "Invalid") -> Invalid | L67: =TEXT(B67,"m") -> 4 | M67: =TEXT(B67,"yyyy") -> 2023 | N67: =IF(D67="Revenue",C67,-ABS(C67)) -> -53590.9 | O67: =IF(D67="Revenue", C67, "") | P67: =IF(D67="Expense", ABS(C67), "") -> 53590.9 | Q67: =IF(O67="","", IF(OR(O67<EDA_Outlier_Analysis!$C$10, O67>EDA_Outlier_Analysis!$C$11), "Outlier", "Normal")) | R67: =IF(P67="","", IF(OR(P67 < EDA_Outlier_Analysis!$F$7, P67 > EDA_Outlier_Analysis!$F$8), "Outlier", "Normal")) -> Normal | S67: =IF(N67="","", IF(OR(N67 <EDA_Outlier_Analysis!$I$10, N67 > EDA_Outlier_Analysis!$I$11), "Outlier", "Normal")) -> Normal
A68: TRX100066 | B68: 44844 | C68: -29061.06 | D68: Expense | E68: Other | F68: Retail | G68: North | I68: VEND1019 | J68: House performance sign deep. | K68: =IF(COUNTIF(Customers!A:A, H68)>0, "Valid", "Invalid") -> Invalid | L68: =TEXT(B68,"m") -> 10 | M68: =TEXT(B68,"yyyy") -> 2022 | N68: =IF(D68="Revenue",C68,-ABS(C68)) -> -29061.06 | O68: =IF(D68="Revenue", C68, "") | P68: =IF(D68="Expense", ABS(C68), "") -> 29061.06 | Q68: =IF(O68="","", IF(OR(O68<EDA_Outlier_Analysis!$C$10, O68>EDA_Outlier_Analysis!$C$11), "Outlier", "Normal")) | R68: =IF(P68="","", IF(OR(P68 < EDA_Outlier_Analysis!$F$7, P68 > EDA_Outlier_Analysis!$F$8), "Outlier", "Normal")) -> Normal | S68: =IF(N68="","", IF(OR(N68 <EDA_Outlier_Analysis!$I$10, N68 > EDA_Outlier_Analysis!$I$11), "Outlier", "Normal")) -> Normal
A69: TRX100067 | B69: 44904 | C69: -48080.35 | D69: Expense | E69: Rent | F69: Retail | G69: North | I69: VEND1030 | J69: Home now local perform by. | K69: =IF(COUNTIF(Customers!A:A, H69)>0, "Valid", "Invalid") -> Invalid | L69: =TEXT(B69,"m") -> 12 | M69: =TEXT(B69,"yyyy") -> 2022 | N69: =IF(D69="Revenue",C69,-ABS(C69)) -> -48080.35 | O69: =IF(D69="Revenue", C69, "") | P69: =IF(D69="Expense", ABS(C69), "") -> 48080.35 | Q69: =IF(O69="","", IF(OR(O69<EDA_Outlier_Analysis!$C$10, O69>EDA_Outlier_Analysis!$C$11), "Outlier", "Normal")) | R69: =IF(P69="","", IF(OR(P69 < EDA_Outlier_Analysis!$F$7, P69 > EDA_Outlier_Analysis!$F$8), "Outlier", "Normal")) -> Normal | S69: =IF(N69="","", IF(OR(N69 <EDA_Outlier_Analysis!$I$10, N69 > EDA_Outlier_Analysis!$I$11), "Outlier", "Normal")) -> Normal
A70: TRX100068 | B70: 44749 | C70: 218024.69 | D70: Revenue | E70: Product | F70: Online | G70: North | H70: CUST10321 | J70: Dog eight perhaps audience past eye. | K70: =IF(COUNTIF(Customers!A:A, H70)>0, "Valid", "Invalid") -> Valid | L70: =TEXT(B70,"m") -> 7 | M70: =TEXT(B70,"yyyy") -> 2022 | N70: =IF(D70="Revenue",C70,-ABS(C70)) -> 218024.69 | O70: =IF(D70="Revenue", C70, "") -> 218024.69 | P70: =IF(D70="Expense", ABS(C70), "") | Q70: =IF(O70="","", IF(OR(O70<EDA_Outlier_Analysis!$C$10, O70>EDA_Outlier_Analysis!$C$11), "Outlier", "Normal")) -> Normal | R70: =IF(P70="","", IF(OR(P70 < EDA_Outlier_Analysis!$F$7, P70 > EDA_Outlier_Analysis!$F$8), "Outlier", "Normal")) | S70: =IF(N70="","", IF(OR(N70 <EDA_Outlier_Analysis!$I$10, N70 > EDA_Outlier_Analysis!$I$11), "Outlier", "Normal")) -> Normal
A71: TRX100069 | B71: 44749 | C71: -38127.82 | D71: Expense | E71: Rent | F71: Enterprise | G71: West | I71: VEND1086 | J71: His another government threat choose water fear. | K71: =IF(COUNTIF(Customers!A:A, H71)>0, "Valid", "Invalid") -> Invalid | L71: =TEXT(B71,"m") -> 7 | M71: =TEXT(B71,"yyyy") -> 2022 | N71: =IF(D71="Revenue",C71,-ABS(C71)) -> -38127.82 | O71: =IF(D71="Revenue", C71, "") | P71: =IF(D71="Expense", ABS(C71), "") -> 38127.82 | Q71: =IF(O71="","", IF(OR(O71<EDA_Outlier_Analysis!$C$10, O71>EDA_Outlier_Analysis!$C$11), "Outlier", "Normal")) | R71: =IF(P71="","", IF(OR(P71 < EDA_Outlier_Analysis!$F$7, P71 > EDA_Outlier_Analysis!$F$8), "Outlier", "Normal")) -> Normal | S71: =IF(N71="","", IF(OR(N71 <EDA_Outlier_Analysis!$I$10, N71 > EDA_Outlier_Analysis!$I$11), "Outlier", "Normal")) -> Normal
A72: TRX100070 | B72: 44989 | C72: -31873.97 | D72: Expense | E72: Rent | F72: Retail | G72: North | I72: VEND1086 | J72: Enjoy keep pass write state even bank. | K72: =IF(COUNTIF(Customers!A:A, H72)>0, "Valid", "Invalid") -> Invalid | L72: =TEXT(B72,"m") -> 3 | M72: =TEXT(B72,"yyyy") -> 2023 | N72: =IF(D72="Revenue",C72,-ABS(C72)) -> -31873.97 | O72: =IF(D72="Revenue", C72, "") | P72: =IF(D72="Expense", ABS(C72), "") -> 31873.97 | Q72: =IF(O72="","", IF(OR(O72<EDA_Outlier_Analysis!$C$10, O72>EDA_Outlier_Analysis!$C$11), "Outlier", "Normal")) | R72: =IF(P72="","", IF(OR(P72 < EDA_Outlier_Analysis!$F$7, P72 > EDA_Outlier_Analysis!$F$8), "Outlier", "Normal")) -> Normal | S72: =IF(N72="","", IF(OR(N72 <EDA_Outlier_Analysis!$I$10, N72 > EDA_Outlier_Analysis!$I$11), "Outlier", "Normal")) -> Normal
A73: TRX100071 | B73: 45082 | C73: 203084.24 | D73: Revenue | E73: Subscription | F73: Online | G73: West | H73: CUST10116 | J73: Possible talk model why we town decade. | K73: =IF(COUNTIF(Customers!A:A, H73)>0, "Valid", "Invalid") -> Valid | L73: =TEXT(B73,"m") -> 6 | M73: =TEXT(B73,"yyyy") -> 2023 | N73: =IF(D73="Revenue",C73,-ABS(C73)) -> 203084.24 | O73: =IF(D73="Revenue", C73, "") -> 203084.24 | P73: =IF(D73="Expense", ABS(C73), "") | Q73: =IF(O73="","", IF(OR(O73<EDA_Outlier_Analysis!$C$10, O73>EDA_Outlier_Analysis!$C$11), "Outlier", "Normal")) -> Normal | R73: =IF(P73="","", IF(OR(P73 < EDA_Outlier_Analysis!$F$7, P73 > EDA_Outlier_Analysis!$F$8), "Outlier", "Normal")) | S73: =IF(N73="","", IF(OR(N73 <EDA_Outlier_Analysis!$I$10, N73 > EDA_Outlier_Analysis!$I$11), "Outlier", "Normal")) -> Normal
A74: TRX100072 | B74: 45290 | C74: 222948.96 | D74: Revenue | E74: Subscription | F74: Online | G74: North | H74: CUST10063 | J74: Black sit anyone language song show watch better. | K74: =IF(COUNTIF(Customers!A:A, H74)>0, "Valid", "Invalid") -> Valid | L74: =TEXT(B74,"m") -> 12 | M74: =TEXT(B74,"yyyy") -> 2023 | N74: =IF(D74="Revenue",C74,-ABS(C74)) -> 222948.96 | O74: =IF(D74="Revenue", C74, "") -> 222948.96 | P74: =IF(D74="Expense", ABS(C74), "") | Q74: =IF(O74="","", IF(OR(O74<EDA_Outlier_Analysis!$C$10, O74>EDA_Outlier_Analysis!$C$11), "Outlier", "Normal")) -> Normal | R74: =IF(P74="","", IF(OR(P74 < EDA_Outlier_Analysis!$F$7, P74 > EDA_Outlier_Analysis!$F$8), "Outlier", "Normal")) | S74: =IF(N74="","", IF(OR(N74 <EDA_Outlier_Analysis!$I$10, N74 > EDA_Outlier_Analysis!$I$11), "Outlier", "Normal")) -> Normal
A75: TRX100073 | B75: 45270 | C75: 238667.54 | D75: Revenue | E75: Product | F75: Enterprise | G75: South | H75: CUST10137 | J75: Rate reflect building guess well TV. | K75: =IF(COUNTIF(Customers!A:A, H75)>0, "Valid", "Invalid") -> Valid | L75: =TEXT(B75,"m") -> 12 | M75: =TEXT(B75,"yyyy") -> 2023 | N75: =IF(D75="Revenue",C75,-ABS(C75)) -> 238667.54 | O75: =IF(D75="Revenue", C75, "") -> 238667.54 | P75: =IF(D75="Expense", ABS(C75), "") | Q75: =IF(O75="","", IF(OR(O75<EDA_Outlier_Analysis!$C$10, O75>EDA_Outlier_Analysis!$C$11), "Outlier", "Normal")) -> Normal | R75: =IF(P75="","", IF(OR(P75 < EDA_Outlier_Analysis!$F$7, P75 > EDA_Outlier_Analysis!$F$8), "Outlier", "Normal")) | S75: =IF(N75="","", IF(OR(N75 <EDA_Outlier_Analysis!$I$10, N75 > EDA_Outlier_Analysis!$I$11), "Outlier", "Normal")) -> Normal
A76: TRX100074 | B76: 44673 | C76: 132774.78 | D76: Revenue | E76: Subscription | F76: Retail | G76: South | H76: CUST10298 | J76: And stop raise somebody nice. | K76: =IF(COUNTIF(Customers!A:A, H76)>0, "Valid", "Invalid") -> Valid | L76: =TEXT(B76,"m") -> 4 | M76: =TEXT(B76,"yyyy") -> 2022 | N76: =IF(D76="Revenue",C76,-ABS(C76)) -> 132774.78 | O76: =IF(D76="Revenue", C76, "") -> 132774.78 | P76: =IF(D76="Expense", ABS(C76), "") | Q76: =IF(O76="","", IF(OR(O76<EDA_Outlier_Analysis!$C$10, O76>EDA_Outlier_Analysis!$C$11), "Outlier", "Normal")) -> Normal | R76: =IF(P76="","", IF(OR(P76 < EDA_Outlier_Analysis!$F$7, P76 > EDA_Outlier_Analysis!$F$8), "Outlier", "Normal")) | S76: =IF(N76="","", IF(OR(N76 <EDA_Outlier_Analysis!$I$10, N76 > EDA_Outlier_Analysis!$I$11), "Outlier", "Normal")) -> Normal
A77: TRX100075 | B77: 45186 | C77: 188545.69 | D77: Revenue | E77: Subscription | F77: Enterprise | G77: North | H77: CUST10187 | J77: Wonder increase hundred today final debate. | K77: =IF(COUNTIF(Customers!A:A, H77)>0, "Valid", "Invalid") -> Valid | L77: =TEXT(B77,"m") -> 9 | M77: =TEXT(B77,"yyyy") -> 2023 | N77: =IF(D77="Revenue",C77,-ABS(C77)) -> 188545.69 | O77: =IF(D77="Revenue", C77, "") -> 188545.69 | P77: =IF(D77="Expense", ABS(C77), "") | Q77: =IF(O77="","", IF(OR(O77<EDA_Outlier_Analysis!$C$10, O77>EDA_Outlier_Analysis!$C$11), "Outlier", "Normal")) -> Normal | R77: =IF(P77="","", IF(OR(P77 < EDA_Outlier_Analysis!$F$7, P77 > EDA_Outlier_Analysis!$F$8), "Outlier", "Normal")) | S77: =IF(N77="","", IF(OR(N77 <EDA_Outlier_Analysis!$I$10, N77 > EDA_Outlier_Analysis!$I$11), "Outlier", "Normal")) -> Normal
A78: TRX100076 | B78: 45056 | C78: 138240.93 | D78: Revenue | E78: Service | F78: Retail | G78: East | H78: CUST10285 | J78: Pick fast one entire. | K78: =IF(COUNTIF(Customers!A:A, H78)>0, "Valid", "Invalid") -> Valid | L78: =TEXT(B78,"m") -> 5 | M78: =TEXT(B78,"yyyy") -> 2023 | N78: =IF(D78="Revenue",C78,-ABS(C78)) -> 138240.93 | O78: =IF(D78="Revenue", C78, "") -> 138240.93 | P78: =IF(D78="Expense", ABS(C78), "") | Q78: =IF(O78="","", IF(OR(O78<EDA_Outlier_Analysis!$C$10, O78>EDA_Outlier_Analysis!$C$11), "Outlier", "Normal")) -> Normal | R78: =IF(P78="","", IF(OR(P78 < EDA_Outlier_Analysis!$F$7, P78 > EDA_Outlier_Analysis!$F$8), "Outlier", "Normal")) | S78: =IF(N78="","", IF(OR(N78 <EDA_Outlier_Analysis!$I$10, N78 > EDA_Outlier_Analysis!$I$11), "Outlier", "Normal")) -> Normal
A79: TRX100077 | B79: 45149 | C79: -14341.81 | D79: Expense | E79: Payroll | F79: Online | G79: North | I79: VEND1095 | J79: East very manager set act perhaps company ability. | K79: =IF(COUNTIF(Customers!A:A, H79)>0, "Valid", "Invalid") -> Invalid | L79: =TEXT(B79,"m") -> 8 | M79: =TEXT(B79,"yyyy") -> 2023 | N79: =IF(D79="Revenue",C79,-ABS(C79)) -> -14341.81 | O79: =IF(D79="Revenue", C79, "") | P79: =IF(D79="Expense", ABS(C79), "") -> 14341.81 | Q79: =IF(O79="","", IF(OR(O79<EDA_Outlier_Analysis!$C$10, O79>EDA_Outlier_Analysis!$C$11), "Outlier", "Normal")) | R79: =IF(P79="","", IF(OR(P79 < EDA_Outlier_Analysis!$F$7, P79 > EDA_Outlier_Analysis!$F$8), "Outlier", "Normal")) -> Outlier | S79: =IF(N79="","", IF(OR(N79 <EDA_Outlier_Analysis!$I$10, N79 > EDA_Outlier_Analysis!$I$11), "Outlier", "Normal")) -> Normal
A80: TRX100078 | B80: 44904 | C80: 163678.6 | D80: Revenue | E80: Product | F80: Enterprise | G80: West | H80: CUST10207 | J80: Three specific late economic serious word. | K80: =IF(COUNTIF(Customers!A:A, H80)>0, "Valid", "Invalid") -> Valid | L80: =TEXT(B80,"m") -> 12 | M80: =TEXT(B80,"yyyy") -> 2022 | N80: =IF(D80="Revenue",C80,-ABS(C80)) -> 163678.6 | O80: =IF(D80="Revenue", C80, "") -> 163678.6 | P80: =IF(D80="Expense", ABS(C80), "") | Q80: =IF(O80="","", IF(OR(O80<EDA_Outlier_Analysis!$C$10, O80>EDA_Outlier_Analysis!$C$11), "Outlier", "Normal")) -> Normal | R80: =IF(P80="","", IF(OR(P80 < EDA_Outlier_Analysis!$F$7, P80 > EDA_Outlier_Analysis!$F$8), "Outlier", "Normal")) | S80: =IF(N80="","", IF(OR(N80 <EDA_Outlier_Analysis!$I$10, N80 > EDA_Outlier_Analysis!$I$11), "Outlier", "Normal")) -> Normal
A81: TRX100079 | B81: 44851 | C81: 198317.9 | D81: Revenue | E81: Product | F81: Enterprise | G81: West | H81: CUST10207 | J81: Continue beyond suffer plant student. | K81: =IF(COUNTIF(Customers!A:A, H81)>0, "Valid", "Invalid") -> Valid | L81: =TEXT(B81,"m") -> 10 | M81: =TEXT(B81,"yyyy") -> 2022 | N81: =IF(D81="Revenue",C81,-ABS(C81)) -> 198317.9 | O81: =IF(D81="Revenue", C81, "") -> 198317.9 | P81: =IF(D81="Expense", ABS(C81), "") | Q81: =IF(O81="","", IF(OR(O81<EDA_Outlier_Analysis!$C$10, O81>EDA_Outlier_Analysis!$C$11), "Outlier", "Normal")) -> Normal | R81: =IF(P81="","", IF(OR(P81 < EDA_Outlier_Analysis!$F$7, P81 > EDA_Outlier_Analysis!$F$8), "Outlier", "Normal")) | S81: =IF(N81="","", IF(OR(N81 <EDA_Outlier_Analysis!$I$10, N81 > EDA_Outlier_Analysis!$I$11), "Outlier", "Normal")) -> Normal
A82: TRX100080 | B82: 45153 | C82: 188616.88 | D82: Revenue | E82: Product | F82: Retail | G82: North | H82: CUST10108 | J82: Doctor surface girl friend everybody thousand under. | K82: =IF(COUNTIF(Customers!A:A, H82)>0, "Valid", "Invalid") -> Valid | L82: =TEXT(B82,"m") -> 8 | M82: =TEXT(B82,"yyyy") -> 2023 | N82: =IF(D82="Revenue",C82,-ABS(C82)) -> 188616.88 | O82: =IF(D82="Revenue", C82, "") -> 188616.88 | P82: =IF(D82="Expense", ABS(C82), "") | Q82: =IF(O82="","", IF(OR(O82<EDA_Outlier_Analysis!$C$10, O82>EDA_Outlier_Analysis!$C$11), "Outlier", "Normal")) -> Normal | R82: =IF(P82="","", IF(OR(P82 < EDA_Outlier_Analysis!$F$7, P82 > EDA_Outlier_Analysis!$F$8), "Outlier", "Normal")) | S82: =IF(N82="","", IF(OR(N82 <EDA_Outlier_Analysis!$I$10, N82 > EDA_Outlier_Analysis!$I$11), "Outlier", "Normal")) -> Normal
A83: TRX100081 | B83: 44738 | C83: -25218.03 | D83: Expense | E83: Marketing | F83: Online | G83: East | I83: VEND1089 | J83: Kid item feeling less player. | K83: =IF(COUNTIF(Customers!A:A, H83)>0, "Valid", "Invalid") -> Invalid | L83: =TEXT(B83,"m") -> 6 | M83: =TEXT(B83,"yyyy") -> 2022 | N83: =IF(D83="Revenue",C83,-ABS(C83)) -> -25218.03 | O83: =IF(D83="Revenue", C83, "") | P83: =IF(D83="Expense", ABS(C83), "") -> 25218.03 | Q83: =IF(O83="","", IF(OR(O83<EDA_Outlier_Analysis!$C$10, O83>EDA_Outlier_Analysis!$C$11), "Outlier", "Normal")) | R83: =IF(P83="","", IF(OR(P83 < EDA_Outlier_Analysis!$F$7, P83 > EDA_Outlier_Analysis!$F$8), "Outlier", "Normal")) -> Outlier | S83: =IF(N83="","", IF(OR(N83 <EDA_Outlier_Analysis!$I$10, N83 > EDA_Outlier_Analysis!$I$11), "Outlier", "Normal")) -> Normal
A84: TRX100082 | B84: 45196 | C84: -15892.26 | D84: Expense | E84: Supplies | F84: Enterprise | G84: South | I84: VEND1025 | J84: Increase mouth your indeed. | K84: =IF(COUNTIF(Customers!A:A, H84)>0, "Valid", "Invalid") -> Invalid | L84: =TEXT(B84,"m") -> 9 | M84: =TEXT(B84,"yyyy") -> 2023 | N84: =IF(D84="Revenue",C84,-ABS(C84)) -> -15892.26 | O84: =IF(D84="Revenue", C84, "") | P84: =IF(D84="Expense", ABS(C84), "") -> 15892.26 | Q84: =IF(O84="","", IF(OR(O84<EDA_Outlier_Analysis!$C$10, O84>EDA_Outlier_Analysis!$C$11), "Outlier", "Normal")) | R84: =IF(P84="","", IF(OR(P84 < EDA_Outlier_Analysis!$F$7, P84 > EDA_Outlier_Analysis!$F$8), "Outlier", "Normal")) -> Outlier | S84: =IF(N84="","", IF(OR(N84 <EDA_Outlier_Analysis!$I$10, N84 > EDA_Outlier_Analysis!$I$11), "Outlier", "Normal")) -> Normal
A85: TRX100083 | B85: 44807 | C85: 199974.44 | D85: Revenue | E85: Subscription | F85: Enterprise | G85: South | H85: CUST10092 | J85: Letter along six agent staff industry who. | K85: =IF(COUNTIF(Customers!A:A, H85)>0, "Valid", "Invalid") -> Valid | L85: =TEXT(B85,"m") -> 9 | M85: =TEXT(B85,"yyyy") -> 2022 | N85: =IF(D85="Revenue",C85,-ABS(C85)) -> 199974.44 | O85: =IF(D85="Revenue", C85, "") -> 199974.44 | P85: =IF(D85="Expense", ABS(C85), "") | Q85: =IF(O85="","", IF(OR(O85<EDA_Outlier_Analysis!$C$10, O85>EDA_Outlier_Analysis!$C$11), "Outlier", "Normal")) -> Normal | R85: =IF(P85="","", IF(OR(P85 < EDA_Outlier_Analysis!$F$7, P85 > EDA_Outlier_Analysis!$F$8), "Outlier", "Normal")) | S85: =IF(N85="","", IF(OR(N85 <EDA_Outlier_Analysis!$I$10, N85 > EDA_Outlier_Analysis!$I$11), "Outlier", "Normal")) -> Normal
A86: TRX100084 | B86: 44686 | C86: 128923.58 | D86: Revenue | E86: Service | F86: Enterprise | G86: North | H86: CUST10082 | J86: Cell prevent goal view water shake matter effect. | K86: =IF(COUNTIF(Customers!A:A, H86)>0, "Valid", "Invalid") -> Valid | L86: =TEXT(B86,"m") -> 5 | M86: =TEXT(B86,"yyyy") -> 2022 | N86: =IF(D86="Revenue",C86,-ABS(C86)) -> 128923.58 | O86: =IF(D86="Revenue", C86, "") -> 128923.58 | P86: =IF(D86="Expense", ABS(C86), "") | Q86: =IF(O86="","", IF(OR(O86<EDA_Outlier_Analysis!$C$10, O86>EDA_Outlier_Analysis!$C$11), "Outlier", "Normal")) -> Normal | R86: =IF(P86="","", IF(OR(P86 < EDA_Outlier_Analysis!$F$7, P86 > EDA_Outlier_Analysis!$F$8), "Outlier", "Normal")) | S86: =IF(N86="","", IF(OR(N86 <EDA_Outlier_Analysis!$I$10, N86 > EDA_Outlier_Analysis!$I$11), "Outlier", "Normal")) -> Normal
A87: TRX100085 | B87: 44982 | C87: 67222.23 | D87: Revenue | E87: Service | F87: Online | G87: West | H87: CUST10209 | J87: End cover a enough speak figure. | K87: =IF(COUNTIF(Customers!A:A, H87)>0, "Valid", "Invalid") -> Valid | L87: =TEXT(B87,"m") -> 2 | M87: =TEXT(B87,"yyyy") -> 2023 | N87: =IF(D87="Revenue",C87,-ABS(C87)) -> 67222.23 | O87: =IF(D87="Revenue", C87, "") -> 67222.23 | P87: =IF(D87="Expense", ABS(C87), "") | Q87: =IF(O87="","", IF(OR(O87<EDA_Outlier_Analysis!$C$10, O87>EDA_Outlier_Analysis!$C$11), "Outlier", "Normal")) -> Normal | R87: =IF(P87="","", IF(OR(P87 < EDA_Outlier_Analysis!$F$7, P87 > EDA_Outlier_Analysis!$F$8), "Outlier", "Normal")) | S87: =IF(N87="","", IF(OR(N87 <EDA_Outlier_Analysis!$I$10, N87 > EDA_Outlier_Analysis!$I$11), "Outlier", "Normal")) -> Normal
A88: TRX100086 | B88: 44923 | C88: 186952.56 | D88: Revenue | E88: Subscription | F88: Online | G88: West | H88: CUST10089 | J88: Economic behind young American artist main personal. | K88: =IF(COUNTIF(Customers!A:A, H88)>0, "Valid", "Invalid") -> Valid | L88: =TEXT(B88,"m") -> 12 | M88: =TEXT(B88,"yyyy") -> 2022 | N88: =IF(D88="Revenue",C88,-ABS(C88)) -> 186952.56 | O88: =IF(D88="Revenue", C88, "") -> 186952.56 | P88: =IF(D88="Expense", ABS(C88), "") | Q88: =IF(O88="","", IF(OR(O88<EDA_Outlier_Analysis!$C$10, O88>EDA_Outlier_Analysis!$C$11), "Outlier", "Normal")) -> Normal | R88: =IF(P88="","", IF(OR(P88 < EDA_Outlier_Analysis!$F$7, P88 > EDA_Outlier_Analysis!$F$8), "Outlier", "Normal")) | S88: =IF(N88="","", IF(OR(N88 <EDA_Outlier_Analysis!$I$10, N88 > EDA_Outlier_Analysis!$I$11), "Outlier", "Normal")) -> Normal
A89: TRX100087 | B89: 45116 | C89: 164462.06 | D89: Revenue | E89: Service | F89: Retail | G89: East | H89: CUST10042 | J89: Girl reveal order deep chair cut sit. | K89: =IF(COUNTIF(Customers!A:A, H89)>0, "Valid", "Invalid") -> Valid | L89: =TEXT(B89,"m") -> 7 | M89: =TEXT(B89,"yyyy") -> 2023 | N89: =IF(D89="Revenue",C89,-ABS(C89)) -> 164462.06 | O89: =IF(D89="Revenue", C89, "") -> 164462.06 | P89: =IF(D89="Expense", ABS(C89), "") | Q89: =IF(O89="","", IF(OR(O89<EDA_Outlier_Analysis!$C$10, O89>EDA_Outlier_Analysis!$C$11), "Outlier", "Normal")) -> Normal | R89: =IF(P89="","", IF(OR(P89 < EDA_Outlier_Analysis!$F$7, P89 > EDA_Outlier_Analysis!$F$8), "Outlier", "Normal")) | S89: =IF(N89="","", IF(OR(N89 <EDA_Outlier_Analysis!$I$10, N89 > EDA_Outlier_Analysis!$I$11), "Outlier", "Normal")) -> Normal
A90: TRX100088 | B90: 44872 | C90: 18077.56 | D90: Equity | E90: Equity | F90: Enterprise | G90: South | J90: Once fact interest difference section remain. | K90: =IF(COUNTIF(Customers!A:A, H90)>0, "Valid", "Invalid") -> Invalid | L90: =TEXT(B90,"m") -> 11 | M90: =TEXT(B90,"yyyy") -> 2022 | N90: =IF(D90="Revenue",C90,-ABS(C90)) -> -18077.56 | O90: =IF(D90="Revenue", C90, "") | P90: =IF(D90="Expense", ABS(C90), "") | Q90: =IF(O90="","", IF(OR(O90<EDA_Outlier_Analysis!$C$10, O90>EDA_Outlier_Analysis!$C$11), "Outlier", "Normal")) | R90: =IF(P90="","", IF(OR(P90 < EDA_Outlier_Analysis!$F$7, P90 > EDA_Outlier_Analysis!$F$8), "Outlier", "Normal")) | S90: =IF(N90="","", IF(OR(N90 <EDA_Outlier_Analysis!$I$10, N90 > EDA_Outlier_Analysis!$I$11), "Outlier", "Normal")) -> Normal
A91: TRX100089 | B91: 45213 | C91: 72337.28 | D91: Revenue | E91: Service | F91: Online | G91: South | H91: CUST10157 | J91: Able finish they defense yet activity. | K91: =IF(COUNTIF(Customers!A:A, H91)>0, "Valid", "Invalid") -> Valid | L91: =TEXT(B91,"m") -> 10 | M91: =TEXT(B91,"yyyy") -> 2023 | N91: =IF(D91="Revenue",C91,-ABS(C91)) -> 72337.28 | O91: =IF(D91="Revenue", C91, "") -> 72337.28 | P91: =IF(D91="Expense", ABS(C91), "") | Q91: =IF(O91="","", IF(OR(O91<EDA_Outlier_Analysis!$C$10, O91>EDA_Outlier_Analysis!$C$11), "Outlier", "Normal")) -> Normal | R91: =IF(P91="","", IF(OR(P91 < EDA_Outlier_Analysis!$F$7, P91 > EDA_Outlier_Analysis!$F$8), "Outlier", "Normal")) | S91: =IF(N91="","", IF(OR(N91 <EDA_Outlier_Analysis!$I$10, N91 > EDA_Outlier_Analysis!$I$11), "Outlier", "Normal")) -> Normal
A92: TRX100090 | B92: 44760 | C92: -40667.5 | D92: Expense | E92: Rent | F92: Online | G92: South | I92: VEND1090 | J92: Instead age animal popular parent baby. | K92: =IF(COUNTIF(Customers!A:A, H92)>0, "Valid", "Invalid") -> Invalid | L92: =TEXT(B92,"m") -> 7 | M92: =TEXT(B92,"yyyy") -> 2022 | N92: =IF(D92="Revenue",C92,-ABS(C92)) -> -40667.5 | O92: =IF(D92="Revenue", C92, "") | P92: =IF(D92="Expense", ABS(C92), "") -> 40667.5 | Q92: =IF(O92="","", IF(OR(O92<EDA_Outlier_Analysis!$C$10, O92>EDA_Outlier_Analysis!$C$11), "Outlier", "Normal")) | R92: =IF(P92="","", IF(OR(P92 < EDA_Outlier_Analysis!$F$7, P92 > EDA_Outlier_Analysis!$F$8), "Outlier", "Normal")) -> Normal | S92: =IF(N92="","", IF(OR(N92 <EDA_Outlier_Analysis!$I$10, N92 > EDA_Outlier_Analysis!$I$11), "Outlier", "Normal")) -> Normal
A93: TRX100091 | B93: 44565 | C93: 177006.22 | D93: Revenue | E93: Product | F93: Retail | G93: West | H93: CUST10212 | J93: Choose per range week. | K93: =IF(COUNTIF(Customers!A:A, H93)>0, "Valid", "Invalid") -> Valid | L93: =TEXT(B93,"m") -> 1 | M93: =TEXT(B93,"yyyy") -> 2022 | N93: =IF(D93="Revenue",C93,-ABS(C93)) -> 177006.22 | O93: =IF(D93="Revenue", C93, "") -> 177006.22 | P93: =IF(D93="Expense", ABS(C93), "") | Q93: =IF(O93="","", IF(OR(O93<EDA_Outlier_Analysis!$C$10, O93>EDA_Outlier_Analysis!$C$11), "Outlier", "Normal")) -> Normal | R93: =IF(P93="","", IF(OR(P93 < EDA_Outlier_Analysis!$F$7, P93 > EDA_Outlier_Analysis!$F$8), "Outlier", "Normal")) | S93: =IF(N93="","", IF(OR(N93 <EDA_Outlier_Analysis!$I$10, N93 > EDA_Outlier_Analysis!$I$11), "Outlier", "Normal")) -> Normal
A94: TRX100092 | B94: 44759 | C94: -33821.98 | D94: Expense | E94: Other | F94: Online | G94: West | I94: VEND1059 | J94: Lay buy bar century. | K94: =IF(COUNTIF(Customers!A:A, H94)>0, "Valid", "Invalid") -> Invalid | L94: =TEXT(B94,"m") -> 7 | M94: =TEXT(B94,"yyyy") -> 2022 | N94: =IF(D94="Revenue",C94,-ABS(C94)) -> -33821.98 | O94: =IF(D94="Revenue", C94, "") | P94: =IF(D94="Expense", ABS(C94), "") -> 33821.98 | Q94: =IF(O94="","", IF(OR(O94<EDA_Outlier_Analysis!$C$10, O94>EDA_Outlier_Analysis!$C$11), "Outlier", "Normal")) | R94: =IF(P94="","", IF(OR(P94 < EDA_Outlier_Analysis!$F$7, P94 > EDA_Outlier_Analysis!$F$8), "Outlier", "Normal")) -> Normal | S94: =IF(N94="","", IF(OR(N94 <EDA_Outlier_Analysis!$I$10, N94 > EDA_Outlier_Analysis!$I$11), "Outlier", "Normal")) -> Normal
A95: TRX100093 | B95: 44749 | C95: 113760.1 | D95: Revenue | E95: Service | F95: Enterprise | G95: South | H95: CUST10232 | J95: Congress whose main matter coach loss executive. | K95: =IF(COUNTIF(Customers!A:A, H95)>0, "Valid", "Invalid") -> Valid | L95: =TEXT(B95,"m") -> 7 | M95: =TEXT(B95,"yyyy") -> 2022 | N95: =IF(D95="Revenue",C95,-ABS(C95)) -> 113760.1 | O95: =IF(D95="Revenue", C95, "") -> 113760.1 | P95: =IF(D95="Expense", ABS(C95), "") | Q95: =IF(O95="","", IF(OR(O95<EDA_Outlier_Analysis!$C$10, O95>EDA_Outlier_Analysis!$C$11), "Outlier", "Normal")) -> Normal | R95: =IF(P95="","", IF(OR(P95 < EDA_Outlier_Analysis!$F$7, P95 > EDA_Outlier_Analysis!$F$8), "Outlier", "Normal")) | S95: =IF(N95="","", IF(OR(N95 <EDA_Outlier_Analysis!$I$10, N95 > EDA_Outlier_Analysis!$I$11), "Outlier", "Normal")) -> Normal
A96: TRX100094 | B96: 44618 | C96: 68040.32 | D96: Revenue | E96: Service | F96: Retail | G96: South | H96: CUST10121 | J96: Bar rock democratic positive live easy grow. | K96: =IF(COUNTIF(Customers!A:A, H96)>0, "Valid", "Invalid") -> Valid | L96: =TEXT(B96,"m") -> 2 | M96: =TEXT(B96,"yyyy") -> 2022 | N96: =IF(D96="Revenue",C96,-ABS(C96)) -> 68040.32 | O96: =IF(D96="Revenue", C96, "") -> 68040.32 | P96: =IF(D96="Expense", ABS(C96), "") | Q96: =IF(O96="","", IF(OR(O96<EDA_Outlier_Analysis!$C$10, O96>EDA_Outlier_Analysis!$C$11), "Outlier", "Normal")) -> Normal | R96: =IF(P96="","", IF(OR(P96 < EDA_Outlier_Analysis!$F$7, P96 > EDA_Outlier_Analysis!$F$8), "Outlier", "Normal")) | S96: =IF(N96="","", IF(OR(N96 <EDA_Outlier_Analysis!$I$10, N96 > EDA_Outlier_Analysis!$I$11), "Outlier", "Normal")) -> Normal
A97: TRX100095 | B97: 45132 | C97: 114168.76 | D97: Revenue | E97: Product | F97: Retail | G97: West | H97: CUST10237 | J97: Certainly believe white money. | K97: =IF(COUNTIF(Customers!A:A, H97)>0, "Valid", "Invalid") -> Valid | L97: =TEXT(B97,"m") -> 7 | M97: =TEXT(B97,"yyyy") -> 2023 | N97: =IF(D97="Revenue",C97,-ABS(C97)) -> 114168.76 | O97: =IF(D97="Revenue", C97, "") -> 114168.76 | P97: =IF(D97="Expense", ABS(C97), "") | Q97: =IF(O97="","", IF(OR(O97<EDA_Outlier_Analysis!$C$10, O97>EDA_Outlier_Analysis!$C$11), "Outlier", "Normal")) -> Normal | R97: =IF(P97="","", IF(OR(P97 < EDA_Outlier_Analysis!$F$7, P97 > EDA_Outlier_Analysis!$F$8), "Outlier", "Normal")) | S97: =IF(N97="","", IF(OR(N97 <EDA_Outlier_Analysis!$I$10, N97 > EDA_Outlier_Analysis!$I$11), "Outlier", "Normal")) -> Normal
A98: TRX100096 | B98: 45034 | C98: 104796.05 | D98: Revenue | E98: Product | F98: Online | G98: West | H98: CUST10266 | J98: Support visit else lead call. | K98: =IF(COUNTIF(Customers!A:A, H98)>0, "Valid", "Invalid") -> Valid | L98: =TEXT(B98,"m") -> 4 | M98: =TEXT(B98,"yyyy") -> 2023 | N98: =IF(D98="Revenue",C98,-ABS(C98)) -> 104796.05 | O98: =IF(D98="Revenue", C98, "") -> 104796.05 | P98: =IF(D98="Expense", ABS(C98), "") | Q98: =IF(O98="","", IF(OR(O98<EDA_Outlier_Analysis!$C$10, O98>EDA_Outlier_Analysis!$C$11), "Outlier", "Normal")) -> Normal | R98: =IF(P98="","", IF(OR(P98 < EDA_Outlier_Analysis!$F$7, P98 > EDA_Outlier_Analysis!$F$8), "Outlier", "Normal")) | S98: =IF(N98="","", IF(OR(N98 <EDA_Outlier_Analysis!$I$10, N98 > EDA_Outlier_Analysis!$I$11), "Outlier", "Normal")) -> Normal
A99: TRX100097 | B99: 44637 | C99: -40864.74 | D99: Expense | E99: Other | F99: Retail | G99: East | I99: VEND1072 | J99: But share truth conference seem TV. | K99: =IF(COUNTIF(Customers!A:A, H99)>0, "Valid", "Invalid") -> Invalid | L99: =TEXT(B99,"m") -> 3 | M99: =TEXT(B99,"yyyy") -> 2022 | N99: =IF(D99="Revenue",C99,-ABS(C99)) -> -40864.74 | O99: =IF(D99="Revenue", C99, "") | P99: =IF(D99="Expense", ABS(C99), "") -> 40864.74 | Q99: =IF(O99="","", IF(OR(O99<EDA_Outlier_Analysis!$C$10, O99>EDA_Outlier_Analysis!$C$11), "Outlier", "Normal")) | R99: =IF(P99="","", IF(OR(P99 < EDA_Outlier_Analysis!$F$7, P99 > EDA_Outlier_Analysis!$F$8), "Outlier", "Normal")) -> Normal | S99: =IF(N99="","", IF(OR(N99 <EDA_Outlier_Analysis!$I$10, N99 > EDA_Outlier_Analysis!$I$11), "Outlier", "Normal")) -> Normal
A100: TRX100098 | B100: 45167 | C100: -10569.47 | D100: Expense | E100: Supplies | F100: Retail | G100: East | I100: VEND1065 | J100: Officer agree interesting nice risk from medical some. | K100: =IF(COUNTIF(Customers!A:A, H100)>0, "Valid", "Invalid") -> Invalid | L100: =TEXT(B100,"m") -> 8 | M100: =TEXT(B100,"yyyy") -> 2023 | N100: =IF(D100="Revenue",C100,-ABS(C100)) -> -10569.47 | O100: =IF(D100="Revenue", C100, "") | P100: =IF(D100="Expense", ABS(C100), "") -> 10569.47 | Q100: =IF(O100="","", IF(OR(O100<EDA_Outlier_Analysis!$C$10, O100>EDA_Outlier_Analysis!$C$11), "Outlier", "Normal")) | R100: =IF(P100="","", IF(OR(P100 < EDA_Outlier_Analysis!$F$7, P100 > EDA_Outlier_Analysis!$F$8), "Outlier", "Normal")) -> Outlier | S100: =IF(N100="","", IF(OR(N100 <EDA_Outlier_Analysis!$I$10, N100 > EDA_Outlier_Analysis!$I$11), "Outlier", "Normal")) -> Normal
...

Sheet Headcount
A1: employee_id | B1: employee_name | C1: business_unit | D1: join_date | E1: status | F1: region | G1: cost_to_company
A2: EMP1000 | B2: Daniel Thornton | C2: Enterprise | D2: 44968 | E2: Active | F2: South | G2: 1566441
A3: EMP1001 | B3: Ashley Burch | C3: Retail | D3: 44084 | E3: Active | F3: West | G3: 1533942
A4: EMP1002 | B4: Angel Perry | C4: Online | D4: 44620 | E4: Active | F4: East | G4: 962333
A5: EMP1003 | B5: Kimberly Harmon | C5: Online | D5: 44484 | E5: Active | F5: North | G5: 503403
A6: EMP1004 | B6: Sarah Smith DDS | C6: Enterprise | D6: 44957 | E6: Active | F6: West | G6: 1051271
A7: EMP1005 | B7: Sierra Jordan | C7: Enterprise | D7: 44945 | E7: Active | F7: South | G7: 731473
A8: EMP1006 | B8: Adam Wood | C8: Enterprise | D8: 43768 | E8: Active | F8: West | G8: 596883
A9: EMP1007 | B9: Keith Collins | C9: Online | D9: 44993 | E9: Active | F9: East | G9: 864597
A10: EMP1008 | B10: Mitchell Kelly | C10: Enterprise | D10: 44438 | E10: Active | F10: North | G10: 1736454
A11: EMP1009 | B11: Jacob Mendez | C11: Enterprise | D11: 45166 | E11: Active | F11: North | G11: 1479884
A12: EMP1010 | B12: William Bryant | C12: Enterprise | D12: 44563 | E12: Active | F12: North | G12: 1160373
A13: EMP1011 | B13: Sean Daniels | C13: Retail | D13: 44741 | E13: Active | F13: South | G13: 1603487
... A201: EMP1199 | B201: Mr. Alec Nelson | C201: Enterprise | D201: 44808 | E201: Inactive | F201: South | G201: 728593

Sheet Vendors
A1: vendor_id | B1: vendor_name | C1: category | D1: region | E1: active
A2: VEND1000 | B2: Johnson-Howard | C2: Supplies | D2: East | E2: Y
A3: VEND1001 | B3: Jensen Ltd | C3: Consulting | D3: South | E3: Y
A4: VEND1002 | B4: Collins Group | C4: Services | D4: North | E4: Y
A5: VEND1003 | B5: Smith, Kirby and Torres | C5: Utilities | D5: North | E5: Y
A6: VEND1004 | B6: Mcgrath, Wheeler and Boyd | C6: Utilities | D6: North | E6: Y
A7: VEND1005 | B7: Cooper-Larson | C7: Supplies | D7: South | E7: Y
A8: VEND1006 | B8: Ward-David | C8: Utilities | D8: South | E8: Y
A9: VEND1007 | B9: Savage Ltd | C9: Utilities | D9: West | E9: Y
A10: VEND1008 | B10: Medina-Lee | C10: Services | D10: South | E10: Y
A11: VEND1009 | B11: Griffith and Sons | C11: Services | D11: East | E11: Y
A12: VEND1010 | B12: Thomas-Santana | C12: Rent | D12: South | E12: Y
... A121: VEND1119 | B121: Graham-Lopez | C121: Consulting | D121: North | E121: N

Sheet EDA_Overview
A1: Datasets
A3: Financial_transactions | B3: Row Count | C3: Total Unique transaction IDs | D3: Start Year | E3: End Year | F3: Business Units | G3: Category
B4: =COUNTA(Financial_Transactions!A2:A10401) -> 10400 | C4: =COUNTA(_xlfn.UNIQUE(Financial_Transactions!A2:A10401)) -> 10400 | D4: =YEAR(MIN(Financial_Transactions!B:B)) -> 2022 | E4: =YEAR(MAX(Financial_Transactions!B:B)) -> 2023 | F4: =_xlfn.TEXTJOIN(", ", TRUE, _xlfn.UNIQUE(Financial_Transactions!F2:F10400)) -> Online, Enterprise, Retail | G4: =_xlfn.TEXTJOIN(", ", TRUE, _xlfn.UNIQUE(Financial_Transactions!E2:E10400)) -> Supplies, Utilities, Subscription, Service, Rent, Marketing, Product, Equity, Other, Payroll, Asset, Liability
A6: Customers | B6: Total customer_ids | C6: Business Segments
B7: =COUNTA(_xlfn.UNIQUE(Customers!A2:A401)) -> 400 | C7: =_xlfn.TEXTJOIN(",",TRUE,_xlfn.UNIQUE(Customers!C2:C401)) -> Online,Enterprise,Retail
A9: Headcount | B9: Total Unique employee_id
B10: =COUNTA(_xlfn.UNIQUE(Headcount!A2:A201)) -> 200
A12: Vendor | B12: Total Unique Vendor_id
B13: =COUNTA(_xlfn.UNIQUE(Vendors!A2:A121)) -> 120
A14: Budget | B14: Key Info
B15: Covers 2022–2023, aligned to all business units
A17: Key points to note
A18: Data spans 2022–2023 with complete monthly coverage
A19: All business units are present across datasets
A20: No missing business units in budget or headcount data
A21: Customer and vendor foreign keys were validated during KPI computation

Sheet EDA_Descriptive_Stats
D1: EXPLORATORY DATA ANALYSIS (EDA) – DESCRIPTIVE STATISTICS
A4: Objective: Summarize key financial KPIs using statistical measures to understand distribution, variability, and trends.
A6: REVENUE – DESCRIPTIVE STATISTICS | E6: EXPENSE – DESCRIPTIVE STATISTICS | H6: PROFIT – DESCRIPTIVE STATISTICS | L6: BUDGET VARIANCE - DESCRIPTIVE STATISTICS
A8: Statistic | B8: Revenue | E8: Statistic | F8: Expense | H8: Statistic | I8: Profit | L8: Statistic | M8: Budget Variance
A9: Mean | B9: =AVERAGEIFS(Financial_Transactions!C:C,Financial_Transactions!D:D,"Revenue") -> 156802.43 | E9: Mean | F9: =ABS(AVERAGEIFS(Financial_Transactions!C:C,Financial_Transactions!D:D,"Expense")) -> 40664.558 | H9: Mean | I9: =AVERAGE(Financial_Transactions!N:N) -> 65556.264 | L9: Mean | M9: =AVERAGE(Budget!H2:H73) -> 8440057.9
A10: Median | B10: {=MEDIAN(_xlfn._xlws.FILTER(Financial_Transactions!C:C, Financial_Transactions!D:D="Revenue"))} -> 153910.43 | E10: Median | F10: {=ABS(MEDIAN(_xlfn._xlws.FILTER(Financial_Transactions!C:C, Financial_Transactions!D:D="Expense")))} -> 40510.71 | H10: Median | I10: =MEDIAN(Financial_Transactions!N:N) -> 78624.65 | L10: Median | M10: =MEDIAN(Budget!H2:H73) -> 8194659.6
A11: Minimum | B11: {=MIN(_xlfn._xlws.FILTER(Financial_Transactions!C:C, Financial_Transactions!D:D="Revenue"))} -> 5000 | E11: Minimum | F11: {=ABS(MIN(_xlfn._xlws.FILTER(Financial_Transactions!C:C, Financial_Transactions!D:D="Expense")))} -> 113310.71 | H11: Minimum | I11: =MIN(Financial_Transactions!N:N) -> -113310.71 | L11: Minimum | M11: =MIN(Budget!H2:H73) -> 3250588.4
A12: Maximum | B12: {=MAX(_xlfn._xlws.FILTER(Financial_Transactions!C:C, Financial_Transactions!D:D="Revenue"))} -> 351386.85 | E12: Maximum | F12: {=ABS(MAX(_xlfn._xlws.FILTER(Financial_Transactions!C:C, Financial_Transactions!D:D="Expense")))} -> 2000 | H12: Maximum | I12: =MAX(Financial_Transactions!N:N) -> 351386.85 | L12: Maximum | M12: =MAX(Budget!H2:H73) -> 15209080
A13: Standard Deviation | B13: {=_xlfn.STDEV.P(_xlfn._xlws.FILTER(Financial_Transactions!C:C, Financial_Transactions!D:D="Revenue"))} -> 51985.266 | E13: Standard Deviation | F13: {=_xlfn.STDEV.P(_xlfn._xlws.FILTER(Financial_Transactions!C:C, Financial_Transactions!D:D="Expense"))} -> 19230.595 | H13: Standard Deviation | I13: =_xlfn.STDEV.P(Financial_Transactions!N:N) -> 104905.64 | L13: Standard Deviation | M13: =_xlfn.STDEV.P(Budget!H2:H73) -> 2793340.2
A14: Interquartile Range (IQR) | B14: {=_xlfn.QUARTILE.INC(_xlfn._xlws.FILTER(Financial_Transactions!C:C, Financial_Transactions!D:D="Revenue"),3)-_xlfn.QUARTILE.INC(_xlfn._xlws.FILTER(Financial_Transactions!C:C, Financial_Transactions!D:D="Revenue"),1)} -> 69004.928 | E14: Interquartile Range (IQR) | F14: {=_xlfn.QUARTILE.INC(_xlfn._xlws.FILTER(Financial_Transactions!C:C, Financial_Transactions!D:D="Expense"),3)-_xlfn.QUARTILE.INC(_xlfn._xlws.FILTER(Financial_Transactions!C:C, Financial_Transactions!D:D="Expense"),1)} -> 26511.16 | H14: Interquartile Range (IQR) | I14: =_xlfn.QUARTILE.INC(Financial_Transactions!N:N,3)-_xlfn.QUARTILE.INC(Financial_Transactions!N:N,1) -> 191115.76 | L14: Interquartile Range (IQR) | M14: =_xlfn.QUARTILE.INC(Budget!H2:H73,3)-_xlfn.QUARTILE.INC(Budget!H2:H73,1) -> 3731206.1
E15: Note use ABS IF WANT THE VALUE IN +
A17: KEY OBSERVATIONS
A18: Revenue | E18: Expense | H18: Profit | L18: Budget Variance
A19: Mean revenue is higher than median → right-skewed distribution | E19: Expense distribution is stable across months | H19: High variance indicates fluctuating profitability | L19: Majority of values positive → frequent over-budget instances
A20: Presence of high-value outlier | E20: Low IQR indicates controlled spending | H20: Some negative profit periods observed | L20: Large variance in Enterprise unit

Sheet KPI
D1: FINANCIAL PERFORMANCE ANALYSIS – KPI DASHBOARD
J4: BUDGET VARIANCE KPI
A5: REVENUE & EXPENSE KPI | F5: PROFIT KPI
J6: Year | K6: Business Unit | L6: Actual Expense | M6: Budgeted Expense | N6: Budget Variance
A7: Year | B7: Business Unit | C7: Revenue | D7: Expense | J7: 2023 | K7: Enterprise | L7: =ABS(SUMIFS(Financial_Transactions!C:C,Financial_Transactions!D:D,"Expense",Financial_Transactions!M:M,KPI!J7,Financial_Transactions!F:F,KPI!K7)) -> 28998688 | M7: =SUMIFS( Budget!E:E, Budget!C:C, KPI!K7, Budget!A:A, KPI!J7 ) -> 17612412 | N7: =L7-M7 -> 11386276
A8: 2023 | B8: Enterprise | C8: =SUMIFS(Financial_Transactions!C:C,Financial_Transactions!D:D,"Revenue",Financial_Transactions!M:M,KPI!A8,Financial_Transactions!F:F,KPI!B8) -> 1.6433538e+08 | D8: =ABS(SUMIFS(Financial_Transactions!C:C,Financial_Transactions!D:D,"Expense",Financial_Transactions!M:M,KPI!A8,Financial_Transactions!F:F,KPI!B8)) -> 28998688 | F8: =SUMIFS(Financial_Transactions!C:C,Financial_Transactions!D:D,"Revenue",Financial_Transactions!K:K,"Valid")-SUMIFS(Financial_Transactions!C:C,Financial_Transactions!D:D,"Expense",Financial_Transactions!K:K,"Valid") -> 8.6460859e+08 | J8: 2023 | K8: Retail | L8: =ABS(SUMIFS(Financial_Transactions!C:C,Financial_Transactions!D:D,"Expense",Financial_Transactions!M:M,KPI!J8,Financial_Transactions!F:F,KPI!K8)) -> 27443202 | M8: =SUMIFS( Budget!E:E, Budget!C:C, KPI!K8, Budget!A:A, KPI!J8 ) -> 15792087 | N8: =L8-M8 -> 11651115
A9: 2023 | B9: Retail | C9: =SUMIFS(Financial_Transactions!C:C,Financial_Transactions!D:D,"Revenue",Financial_Transactions!M:M,KPI!A9,Financial_Transactions!F:F,KPI!B9) -> 1.5615796e+08 | D9: =ABS(SUMIFS(Financial_Transactions!C:C,Financial_Transactions!D:D,"Expense",Financial_Transactions!M:M,KPI!A9,Financial_Transactions!F:F,KPI!B9)) -> 27443202 | J9: 2023 | K9: Online | L9: =ABS(SUMIFS(Financial_Transactions!C:C,Financial_Transactions!D:D,"Expense",Financial_Transactions!M:M,KPI!J9,Financial_Transactions!F:F,KPI!K9)) -> 27438101 | M9: =SUMIFS( Budget!E:E, Budget!C:C, KPI!K9, Budget!A:A, KPI!J9 ) -> 19043590 | N9: =L9-M9 -> 8394510.8
A10: 2023 | B10: Online | C10: =SUMIFS(Financial_Transactions!C:C,Financial_Transactions!D:D,"Revenue",Financial_Transactions!M:M,KPI!A10,Financial_Transactions!F:F,KPI!B10) -> 1.6668913e+08 | D10: =ABS(SUMIFS(Financial_Transactions!C:C,Financial_Transactions!D:D,"Expense",Financial_Transactions!M:M,KPI!A10,Financial_Transactions!F:F,KPI!B10)) -> 27438101 | J10: 2022 | K10: Enterprise | L10: =ABS(SUMIFS(Financial_Transactions!C:C,Financial_Transactions!D:D,"Expense",Financial_Transactions!F:F,KPI!K10,Financial_Transactions!M:M,KPI!J10)) -> 28023931 | M10: =SUMIFS( Budget!E:E, Budget!C:C, KPI!K10, Budget!A:A, KPI!J10 ) -> 15977111 | N10: =L10-M10 -> 12046820
A11: 2022 | B11: Enterprise | C11: =SUMIFS(Financial_Transactions!C:C,Financial_Transactions!D:D,"Revenue",Financial_Transactions!M:M,KPI!A11,Financial_Transactions!F:F,KPI!B11) -> 1.1706183e+08 | D11: =ABS(SUMIFS(Financial_Transactions!C:C,Financial_Transactions!D:D,"Expense",Financial_Transactions!M:M,KPI!A11,Financial_Transactions!F:F,KPI!B11)) -> 28023931 | J11: 2022 | K11: Retail | L11: =ABS(SUMIFS(Financial_Transactions!C:C,Financial_Transactions!D:D,"Expense",Financial_Transactions!F:F,KPI!K11,Financial_Transactions!M:M,KPI!J11)) -> 27971942 | M11: =SUMIFS( Budget!E:E, Budget!C:C, KPI!K11, Budget!A:A, KPI!J11 ) -> 17749649 | N11: =L11-M11 -> 10222293
A12: 2022 | B12: Retail | C12: =SUMIFS(Financial_Transactions!C:C,Financial_Transactions!D:D,"Revenue",Financial_Transactions!M:M,KPI!A12,Financial_Transactions!F:F,KPI!B12) -> 1.2952051e+08 | D12: =ABS(SUMIFS(Financial_Transactions!C:C,Financial_Transactions!D:D,"Expense",Financial_Transactions!M:M,KPI!A12,Financial_Transactions!F:F,KPI!B12)) -> 27971942 | J12: 2022 | K12: Online | L12: =ABS(SUMIFS(Financial_Transactions!C:C,Financial_Transactions!D:D,"Expense",Financial_Transactions!F:F,KPI!K12,Financial_Transactions!M:M,KPI!J12)) -> 27865437 | M12: =SUMIFS( Budget!E:E, Budget!C:C, KPI!K12, Budget!A:A, KPI!J12 ) -> 18090420 | N12: =L12-M12 -> 9775016.9
A13: 2022 | B13: Online | C13: =SUMIFS(Financial_Transactions!C:C,Financial_Transactions!D:D,"Revenue",Financial_Transactions!M:M,KPI!A13,Financial_Transactions!F:F,KPI!B13) -> 1.3084379e+08 | D13: =ABS(SUMIFS(Financial_Transactions!C:C,Financial_Transactions!D:D,"Expense",Financial_Transactions!M:M,KPI!A13,Financial_Transactions!F:F,KPI!B13)) -> 27865437
A15: Expense per vendor | E15: COST PER EMPLOYEE BY BUSINESS UNIT | J15: REVENUE PER CUSTOMER KPI
A17: Business Unit | B17: Expense per Vendor | E17: Business Unit | F17: Cost per employee | J17: Business Unit | K17: Revenue per Customer
A18: Enterprise | B18: {=ABS(SUMIFS( Financial_Transactions!C:C, Financial_Transactions!D:D,"Expense", Financial_Transactions!F:F,KPI!A18 )/COUNTA(_xlfn.UNIQUE(_xlfn._xlws.FILTER(Financial_Transactions!I:I,(Financial_Transactions!F:F=KPI!A18)*(Financial_Transactions!D:D="Expense")))))} -> 475188.49 | E18: Enterprise | F18: =SUMIFS(Headcount!G:G,Headcount!C:C,KPI!E18)/COUNTA(Headcount!A:A) -> 337313.96 | J18: Enterprise | K18: {=SUMIFS(Financial_Transactions!C:C,Financial_Transactions!D:D,"Revenue",Financial_Transactions!F:F,KPI!J18,Financial_Transactions!K:K,"valid")/COUNTA(_xlfn.UNIQUE(_xlfn._xlws.FILTER(Financial_Transactions!H:H,(Financial_Transactions!D:D="Revenue")*(Financial_Transactions!F:F=KPI!J18)*(Financial_Transactions!K:K="Valid"))))} -> 760532.99
A19: Retail | B19: {=ABS(SUMIFS( Financial_Transactions!C:C, Financial_Transactions!D:D,"Expense", Financial_Transactions!F:F,KPI!A19 )/COUNTA(_xlfn.UNIQUE(_xlfn._xlws.FILTER(Financial_Transactions!I:I,(Financial_Transactions!F:F=KPI!A19)*(Financial_Transactions!D:D="Expense")))))} -> 461792.86 | E19: Retail | F19: =SUMIFS(Headcount!G:G,Headcount!C:C,KPI!E19)/COUNTA(Headcount!A:A) -> 364607.16 | J19: Retail | K19: {=SUMIFS(Financial_Transactions!C:C,Financial_Transactions!D:D,"Revenue",Financial_Transactions!F:F,KPI!J19,Financial_Transactions!K:K,"valid")/COUNTA(_xlfn.UNIQUE(_xlfn._xlws.FILTER(Financial_Transactions!H:H,(Financial_Transactions!D:D="Revenue")*(Financial_Transactions!F:F=KPI!J19)*(Financial_Transactions!K:K="Valid"))))} -> 772103.96
A20: Online | B20: {=ABS(SUMIFS( Financial_Transactions!C:C, Financial_Transactions!D:D,"Expense", Financial_Transactions!F:F,KPI!A20 )/COUNTA(_xlfn.UNIQUE(_xlfn._xlws.FILTER(Financial_Transactions!I:I,(Financial_Transactions!F:F=KPI!A20)*(Financial_Transactions!D:D="Expense")))))} -> 460862.81 | E20: Online | F20: =SUMIFS(Headcount!G:G,Headcount!C:C,KPI!E20)/COUNTA(Headcount!A:A) -> 406663.82 | J20: Online | K20: {=SUMIFS(Financial_Transactions!C:C,Financial_Transactions!D:D,"Revenue",Financial_Transactions!F:F,KPI!J20,Financial_Transactions!K:K,"valid")/COUNTA(_xlfn.UNIQUE(_xlfn._xlws.FILTER(Financial_Transactions!H:H,(Financial_Transactions!D:D="Revenue")*(Financial_Transactions!F:F=KPI!J20)*(Financial_Transactions!K:K="Valid"))))} -> 799819.68

Sheet DISTRIBUTION ANALYSIS (HISTOGRA
E1: DISTRIBUTION ANALYSIS (HISTOGRAMS)
A4: Objective | B4: Understand how Revenue, Expense, Profit, and Budget Variance values are spread and whether they are skewed, concentrated, or volatile.
A22: Interpretation | J22: Interpretation
A23: Distribution is right-skewed | J23: Distribution is relatively stable
A24: Majority of transactions are low-to-mid value | J24: Most expenses fall within a narrow range
A25: Few high-value revenue transactions dominate totals | J25: Suggests controlled cost structure
A26: Indicates revenue concentration risk | J26: Limited extreme expense events
A45: Interpretation | J45: Interpretation
A46: Distribution spans both positive and negative values | J46: Distribution skewed toward positive values
A47: High spread indicates profit volatility | J47: Indicates frequent budget overruns
A48: Presence of loss-making transactions | J48: Variance magnitude differs across business units
A49: Profitability not uniform across periods | J49: Distribution based on aggregated budget records, resulting in fewer observations.

Sheet EDA_Outlier_Analysis
E2: OUTLIER ANALYSIS — IQR METHOD
A5: Revenue Outlier Analysis | E5: Expense Outlier Analysis | H5: PROFIT OUTLIER ANALYSIS | L5: BUDGET VARIANCE OUTLIER ANALYSIS
A6: Statistic | C6: Value | E6: Statistic | F6: Value | H6: Statistic | I6: Value | L6: Statistic | M6: Value
A7: Q1 | C7: =_xlfn.QUARTILE.INC(Financial_Transactions!O:O,1) -> 121379.81 | E7: Q1 | F7: =_xlfn.QUARTILE.INC(Financial_Transactions!P:P,1) -> 27137.34 | H7: Q1 | I7: =_xlfn.QUARTILE.INC(Financial_Transactions!N:N,1) -> -33812.21 | L7: Q1 | M7: =_xlfn.QUARTILE.INC(Budget!H:H,1) -> 6460452.4
A8: Q3 | C8: =_xlfn.QUARTILE.INC(Financial_Transactions!O:O,3) -> 190384.74 | E8: Q3 | F8: =_xlfn.QUARTILE.INC(Financial_Transactions!P:P,3) -> 53648.5 | H8: Q3 | I8: =_xlfn.QUARTILE.INC(Financial_Transactions!N:N,3) -> 157303.55 | L8: Q3 | M8: =_xlfn.QUARTILE.INC(Budget!H:H,3) -> 10191659
A9: IQR | C9: =C8-C7 -> 69004.928 | E9: IQR | F9: =F8-F7 -> 26511.16 | H9: IQR | I9: =I8-I7 -> 191115.76 | L9: IQR | M9: =M8-M7 -> 3731206.1
A10: Lower Bound | C10: =C7-1.5*C9 -> 17872.419 | E10: Lower Bound | F10: =F7-1.5*F9 -> -12629.4 | H10: Lower Bound | I10: =I7-1.5*I9 -> -320485.85 | L10: Lower Bound | M10: =M7-1.5*M9 -> 863643.21
A11: Upper Bound | C11: =C8+1.5*C9 -> 293892.13 | E11: Upper Bound | F11: =F8+1.5*F9 -> 93415.24 | H11: Upper Bound | I11: =I8+1.5*I9 -> 443977.2 | L11: Upper Bound | M11: =M8+1.5*M9 -> 15788468
A12: Total Observations | C12: =COUNT(Financial_Transactions!O:O) -> 5514 | E12: Total Observations | F12: =COUNT(Financial_Transactions!P:P) -> 4125 | H12: Total Observations | I12: =COUNT(Financial_Transactions!N:N) -> 10400 | L12: Total Observations | M12: =COUNT(Budget!H:H) -> 72
A13: Outlier Count | C13: =COUNTIF(Financial_Transactions!Q:Q,"Outlier") -> 51 | E13: Outlier Count | F13: =COUNTIF(Financial_Transactions!R:R,"Outlier") -> 2062 | H13: Outlier Count | I13: =COUNTIF(Financial_Transactions!S:S,"Outlier") -> 0 | L13: Outlier Count | M13: =COUNTIF(Budget!I:I,"Outlier") -> 0
A14: % Outliers | C14: =C13/C12 -> 0.0092491839 | E14: % Outliers | F14: =F13/F12 -> 0.49987879 | H14: % Outliers | I14: =I13/I11 -> 0 | L14: % Outliers | M14: =M13/M12 -> 0

Sheet EDA_Time_Series
D1: EXPLORATORY DATA ANALYSIS (EDA) — TIME SERIES & TREND ANALYSIS
A4: Objective: Analyze monthly trends in Revenue, Expense, Profit, and Budget Variance to identify growth patterns, seasonality, and volatility across 2022–2023.
A6: Year | B6: Month_no | C6: Month_name | D6: Revenue | E6: Expense | F6: Profit | G6: Budget Variance | H6: Expense_helper_col
A7: 2022 | B7: 1 | C7: =TEXT(DATE(A7, B7, 1), "mmmm") -> January | D7: =SUMIFS(Financial_Transactions!C:C,Financial_Transactions!D:D,"Revenue",Financial_Transactions!M:M,EDA_Time_Series!A7,Financial_Transactions!L:L,EDA_Time_Series!B7) -> 25538098 | E7: =SUMIFS(Financial_Transactions!C:C,Financial_Transactions!D:D,"Expense",Financial_Transactions!M:M,EDA_Time_Series!A7,Financial_Transactions!L:L,EDA_Time_Series!B7) -> -7399263.9 | F7: =D7-E7 -> 32937362 | G7: =SUMIFS(Budget!H:H,Budget!A:A,EDA_Time_Series!A7,Budget!B:B,EDA_Time_Series!B7) -> 14748460 | H7: =ABS(E7) -> 7399263.9
A8: 2022 | B8: 2 | C8: =TEXT(DATE(A8, B8, 1), "mmmm") -> February | D8: =SUMIFS(Financial_Transactions!C:C,Financial_Transactions!D:D,"Revenue",Financial_Transactions!M:M,EDA_Time_Series!A8,Financial_Transactions!L:L,EDA_Time_Series!B8) -> 22787660 | E8: =SUMIFS(Financial_Transactions!C:C,Financial_Transactions!D:D,"Expense",Financial_Transactions!M:M,EDA_Time_Series!A8,Financial_Transactions!L:L,EDA_Time_Series!B8) -> -6128841.5 | F8: =D8-E8 -> 28916501 | G8: =SUMIFS(Budget!H:H,Budget!A:A,EDA_Time_Series!A8,Budget!B:B,EDA_Time_Series!B8) -> 13528123 | H8: =ABS(E8) -> 6128841.5
A9: 2022 | B9: 3 | C9: =TEXT(DATE(A9, B9, 1), "mmmm") -> March | D9: =SUMIFS(Financial_Transactions!C:C,Financial_Transactions!D:D,"Revenue",Financial_Transactions!M:M,EDA_Time_Series!A9,Financial_Transactions!L:L,EDA_Time_Series!B9) -> 25839879 | E9: =SUMIFS(Financial_Transactions!C:C,Financial_Transactions!D:D,"Expense",Financial_Transactions!M:M,EDA_Time_Series!A9,Financial_Transactions!L:L,EDA_Time_Series!B9) -> -6837846.5 | F9: =D9-E9 -> 32677725 | G9: =SUMIFS(Budget!H:H,Budget!A:A,EDA_Time_Series!A9,Budget!B:B,EDA_Time_Series!B9) -> 15990706 | H9: =ABS(E9) -> 6837846.5
A10: 2022 | B10: 4 | C10: =TEXT(DATE(A10, B10, 1), "mmmm") -> April | D10: =SUMIFS(Financial_Transactions!C:C,Financial_Transactions!D:D,"Revenue",Financial_Transactions!M:M,EDA_Time_Series!A10,Financial_Transactions!L:L,EDA_Time_Series!B10) -> 32862479 | E10: =SUMIFS(Financial_Transactions!C:C,Financial_Transactions!D:D,"Expense",Financial_Transactions!M:M,EDA_Time_Series!A10,Financial_Transactions!L:L,EDA_Time_Series!B10) -> -7543282 | F10: =D10-E10 -> 40405761 | G10: =SUMIFS(Budget!H:H,Budget!A:A,EDA_Time_Series!A10,Budget!B:B,EDA_Time_Series!B10) -> 21766286 | H10: =ABS(E10) -> 7543282
A11: 2022 | B11: 5 | C11: =TEXT(DATE(A11, B11, 1), "mmmm") -> May | D11: =SUMIFS(Financial_Transactions!C:C,Financial_Transactions!D:D,"Revenue",Financial_Transactions!M:M,EDA_Time_Series!A11,Financial_Transactions!L:L,EDA_Time_Series!B11) -> 26932607 | E11: =SUMIFS(Financial_Transactions!C:C,Financial_Transactions!D:D,"Expense",Financial_Transactions!M:M,EDA_Time_Series!A11,Financial_Transactions!L:L,EDA_Time_Series!B11) -> -7347552.8 | F11: =D11-E11 -> 34280160 | G11: =SUMIFS(Budget!H:H,Budget!A:A,EDA_Time_Series!A11,Budget!B:B,EDA_Time_Series!B11) -> 16120062 | H11: =ABS(E11) -> 7347552.8
A12: 2022 | B12: 6 | C12: =TEXT(DATE(A12, B12, 1), "mmmm") -> June | D12: =SUMIFS(Financial_Transactions!C:C,Financial_Transactions!D:D,"Revenue",Financial_Transactions!M:M,EDA_Time_Series!A12,Financial_Transactions!L:L,EDA_Time_Series!B12) -> 34033298 | E12: =SUMIFS(Financial_Transactions!C:C,Financial_Transactions!D:D,"Expense",Financial_Transactions!M:M,EDA_Time_Series!A12,Financial_Transactions!L:L,EDA_Time_Series!B12) -> -6923308.4 | F12: =D12-E12 -> 40956607 | G12: =SUMIFS(Budget!H:H,Budget!A:A,EDA_Time_Series!A12,Budget!B:B,EDA_Time_Series!B12) -> 22485071 | H12: =ABS(E12) -> 6923308.4
A13: 2022 | B13: 7 | C13: =TEXT(DATE(A13, B13, 1), "mmmm") -> July | D13: =SUMIFS(Financial_Transactions!C:C,Financial_Transactions!D:D,"Revenue",Financial_Transactions!M:M,EDA_Time_Series!A13,Financial_Transactions!L:L,EDA_Time_Series!B13) -> 32543434 | E13: =SUMIFS(Financial_Transactions!C:C,Financial_Transactions!D:D,"Expense",Financial_Transactions!M:M,EDA_Time_Series!A13,Financial_Transactions!L:L,EDA_Time_Series!B13) -> -7103985.8 | F13: =D13-E13 -> 39647419 | G13: =SUMIFS(Budget!H:H,Budget!A:A,EDA_Time_Series!A13,Budget!B:B,EDA_Time_Series!B13) -> 21529968 | H13: =ABS(E13) -> 7103985.8
A14: 2022 | B14: 8 | C14: =TEXT(DATE(A14, B14, 1), "mmmm") -> August | D14: =SUMIFS(Financial_Transactions!C:C,Financial_Transactions!D:D,"Revenue",Financial_Transactions!M:M,EDA_Time_Series!A14,Financial_Transactions!L:L,EDA_Time_Series!B14) -> 36856527 | E14: =SUMIFS(Financial_Transactions!C:C,Financial_Transactions!D:D,"Expense",Financial_Transactions!M:M,EDA_Time_Series!A14,Financial_Transactions!L:L,EDA_Time_Series!B14) -> -7371098 | F14: =D14-E14 -> 44227625 | G14: =SUMIFS(Budget!H:H,Budget!A:A,EDA_Time_Series!A14,Budget!B:B,EDA_Time_Series!B14) -> 25506169 | H14: =ABS(E14) -> 7371098
A15: 2022 | B15: 9 | C15: =TEXT(DATE(A15, B15, 1), "mmmm") -> September | D15: =SUMIFS(Financial_Transactions!C:C,Financial_Transactions!D:D,"Revenue",Financial_Transactions!M:M,EDA_Time_Series!A15,Financial_Transactions!L:L,EDA_Time_Series!B15) -> 32948507 | E15: =SUMIFS(Financial_Transactions!C:C,Financial_Transactions!D:D,"Expense",Financial_Transactions!M:M,EDA_Time_Series!A15,Financial_Transactions!L:L,EDA_Time_Series!B15) -> -6119524.5 | F15: =D15-E15 -> 39068032 | G15: =SUMIFS(Budget!H:H,Budget!A:A,EDA_Time_Series!A15,Budget!B:B,EDA_Time_Series!B15) -> 23074781 | H15: =ABS(E15) -> 6119524.5
A16: 2022 | B16: 10 | C16: =TEXT(DATE(A16, B16, 1), "mmmm") -> October | D16: =SUMIFS(Financial_Transactions!C:C,Financial_Transactions!D:D,"Revenue",Financial_Transactions!M:M,EDA_Time_Series!A16,Financial_Transactions!L:L,EDA_Time_Series!B16) -> 37149413 | E16: =SUMIFS(Financial_Transactions!C:C,Financial_Transactions!D:D,"Expense",Financial_Transactions!M:M,EDA_Time_Series!A16,Financial_Transactions!L:L,EDA_Time_Series!B16) -> -7174351.2 | F16: =D16-E16 -> 44323765 | G16: =SUMIFS(Budget!H:H,Budget!A:A,EDA_Time_Series!A16,Budget!B:B,EDA_Time_Series!B16) -> 26698439 | H16: =ABS(E16) -> 7174351.2
A17: 2022 | B17: 11 | C17: =TEXT(DATE(A17, B17, 1), "mmmm") -> November | D17: =SUMIFS(Financial_Transactions!C:C,Financial_Transactions!D:D,"Revenue",Financial_Transactions!M:M,EDA_Time_Series!A17,Financial_Transactions!L:L,EDA_Time_Series!B17) -> 35853481 | E17: =SUMIFS(Financial_Transactions!C:C,Financial_Transactions!D:D,"Expense",Financial_Transactions!M:M,EDA_Time_Series!A17,Financial_Transactions!L:L,EDA_Time_Series!B17) -> -6342891.5 | F17: =D17-E17 -> 42196373 | G17: =SUMIFS(Budget!H:H,Budget!A:A,EDA_Time_Series!A17,Budget!B:B,EDA_Time_Series!B17) -> 25586770 | H17: =ABS(E17) -> 6342891.5
A18: 2022 | B18: 12 | C18: =TEXT(DATE(A18, B18, 1), "mmmm") -> December | D18: =SUMIFS(Financial_Transactions!C:C,Financial_Transactions!D:D,"Revenue",Financial_Transactions!M:M,EDA_Time_Series!A18,Financial_Transactions!L:L,EDA_Time_Series!B18) -> 34080746 | E18: =SUMIFS(Financial_Transactions!C:C,Financial_Transactions!D:D,"Expense",Financial_Transactions!M:M,EDA_Time_Series!A18,Financial_Transactions!L:L,EDA_Time_Series!B18) -> -7569363.1 | F18: =D18-E18 -> 41650110 | G18: =SUMIFS(Budget!H:H,Budget!A:A,EDA_Time_Series!A18,Budget!B:B,EDA_Time_Series!B18) -> 22586389 | H18: =ABS(E18) -> 7569363.1
... A30: 2023 | B30: 12 | C30: =TEXT(DATE(A30, B30, 1), "mmmm") -> December | D30: =SUMIFS(Financial_Transactions!C:C,Financial_Transactions!D:D,"Revenue",Financial_Transactions!M:M,EDA_Time_Series!A30,Financial_Transactions!L:L,EDA_Time_Series!B30) -> 52720899 | E30: =SUMIFS(Financial_Transactions!C:C,Financial_Transactions!D:D,"Expense",Financial_Transactions!M:M,EDA_Time_Series!A30,Financial_Transactions!L:L,EDA_Time_Series!B30) -> -6234683.8 | F30: =D30-E30 -> 58955583 | G30: =SUMIFS(Budget!H:H,Budget!A:A,EDA_Time_Series!A30,Budget!B:B,EDA_Time_Series!B30) -> 42544228 | H30: =ABS(E30) -> 6234683.8
A33: Note: Expenses are stored as negative values to reflect cash outflow.

Sheet EDA_Time_Trends_Charts
C1: EXPLORATORY DATA ANALYSIS (EDA) — TIME SERIES & TREND ANALYSIS
A3: Objective:
A4: Analyze monthly trends in Revenue, Expense, Profit, and Budget Variance to identify growth patterns, seasonality, volatility, and budget discipline across 2022–2023.
A6: CHART 1: REVENUE TREND (MONTHLY) | L6: CHART 3: PROFIT TREND (MONTHLY)
A7: Objective->Understand growth pattern, seasonality, and volatility in revenue across 2022–2023. | L7: Objective->Assess profitability consistency and risk periods.
B24: Key Insight: | L24: Key Insight:
B25: • Revenue shows a generally upward trend with noticeable month-to-month volatility. | L25: • Profitability is volatile due to revenue concentration and expense fluctuations.
B26: • Revenue growth accelerates in the second half of the year, indicating seasonal demand. | L26: • Certain months experience lower margins, increasing financial risk.
A28: CHART 2: EXPENSE TREND (MONTHLY) | L28: CHART 4: BUDGET VARIANCE TREND
A29: Objective-> Analyze cost behavior, stability, and spikes over time. | L29: Objective-> Identify over-budget and under-budget periods.
B46: Key Insight: | L46: Key Insight:
B47: • Expenses remain relatively stable across months. | L47: • Budget variance remains mostly positive, indicating frequent overspending.
B48: • Occasional spikes suggest one-time or event-driven costs rather than structural issues. | L48: • Larger deviations appear in later months, signaling weak budget control.
A51: Overall Trend Summary
A53: • Revenue growth is present but uneven, driven by a few high-performing months.
A54: • Expense control appears stable, though not tightly optimized.
A55: • Profit volatility suggests dependency on revenue spikes rather than steady margins.
A56: • Budget overruns are frequent, indicating a need for stronger financial planning and controls.

Sheet EDA_Trend_Insights
B1: EDA — Business Insights from Time Series Trends (2022–2023)
A4: Objective:
A5: Translate time-series patterns in Revenue, Expense, Profit, and Budget Variance into actionable business insights and financial risks.
A7: Metric | B7: Observed Trend | C7: Business Insight | D7: Risk / Implication
A8: Revenue | B8: Revenue shows a general upward trend across the two-year period. Growth is uneven, with sharp increases in select months. Later months consistently outperform earlier periods. | C8: Revenue growth is driven by a limited number of high-performing months. Indicates revenue concentration risk, rather than stable recurring income. Business may be dependent on seasonal demand or large transactions. | D8: High dependency on a few periods/customers increases revenue concentration risk
A9: Expense | B9: Expenses remain relatively stable month-over-month. Minor spikes appear, but no extreme cost surges. Expense trend is flatter compared to revenue trend. | C9: Indicates controlled cost structure. Expenses do not scale proportionally with revenue growth. | D9: Sudden spikes may indicate event-based or discretionary spending requiring review Opportunity Identified But here a Operating leverage opportunity Stable costs + growing revenue → potential margin expansion if revenue becomes consistent.
A10: Profit | B10: Profit trend is volatile, fluctuating across months. Some months show noticeably lower profitability. Profit does not increase linearly with revenue. | C10: Profitability is sensitive to revenue fluctuations. High expenses during moderate-revenue months compress margins. | D10: Margin instability risk as inconsistent profit makes forecasting and long-term planning difficult.
A11: Budget Variance | B11: Budget variance is predominantly positive. Overspending occurs in most months. Variance magnitude increases in later periods. | C11: Budgets are not realistically aligned with actual cost behavior. Weak monitoring or delayed corrective actions. | D11: Weak budget discipline may lead to cash flow stress and inefficient resource allocation
A13: EXECUTIVE SUMMARY
A14: • Revenue growth exists but is inconsistent and concentrated in select periods.
A15: • Cost structure is stable, suggesting efficiency but potential underinvestment or rigidity.
A16: • Profitability is volatile, exposing the business to earnings risk.
A17: • Budget overruns are frequent, indicating gaps in financial planning and control.
A20: Strategic Recommendations
A21: • Diversify revenue streams to reduce dependency on peak months.
A22: • Improve budget forecasting using historical variance patterns.
A23: •Introduce early-warning alerts for budget overruns.
A24: • Focus on margin optimization during mid-performing months.
